Workbook

Sheet 00_README
B2: Digitaler Assistent – Szenario- und Nutzenmodell
B4: Zweck | C4: Kosten- und Nutzenanalyse für Digitalen Assistenten bei der Landi. 5 Szenarien: Copilot Studio, GCP Vertex AI, Azure Komponenten (GPT-5.1 CH North), Open Source Azure, GCP Custom. ZenAI entfernt. 6 priorisierte Use Cases (alle 100% generativ). 600 Nutzer · 6 Kernsysteme · 5-Jahres-TCO.
B5: Arbeitsweise | C5: 1) Annahmen in 02_INPUTS prüfen (bleiben von Landi bestätigt). 2) Szenario-Hebel in 03_SZENARIOS anpassen. 3) Ergebnisse in 01_EXEC_SUMMARY und 07_VALUE_CASE ablesen.
B6: Wichtiger Modellentscheid | C6: Die operative Landi-Top-down-Schätzung und die Workshop-Bottom-up-Schätzung werden bewusst parallel gezeigt. Der Basiscase nutzt die konservative Effizienzsicht; kommerzielle Upside ist standardmässig deaktiviert.
B7: Hinweis zu Preisen & Annahmen | C7: Microsoft- und Azure-Preise sind region-, vertrag- und FX-abhängig. Deshalb sind Preise als parametrisierbare Annahmen aufgebaut und die Quellen im Sheet 08_SOURCES dokumentiert.
B8: Hinweis | C8: Gelbe Zellen = editierbare Annahmen. Formeln sind schwarz/grün. Kommerzielle Upside kann in 02_INPUTS aktiviert werden.

Sheet 01_EXEC_SUMMARY
B2: Executive Summary – Szenariovergleich Digitaler Assistent
B4: 1) Executive Übersicht
B5: Kernaussage | C5: Copilot Studio | D5: Azure Komponenten | E5: Open Source auf Azure | F5: GCP Vertex AI | G5: GCP Kompontenten | H5: Kommentar
B6: Strategische Analyse | C6: GPT-5 MS-managed; Günstig wenn M365 Copilot; Custom Connectors nötig; keine CH-LLM-Residenz. | D6: GPT-5.1 in CH North; volle CH-Residenz; Token CHF 95/Mo; beste Wahl für GPT-5.1+CH+SAP/ERP. | E6: Llama 4/Phi-4; kein OpenAI-Lock-in; CH North möglich; LLM-Ops nötig; längste Delivery. | F6: GCP Agent Builder + Gemini 3.1; günstigstes OPEX korrigiert; keine CH-Residenz; GCP-Strategie. | G6: Cloud Run+ADK+Gemini direkt+Firestore; günstigstes all-in OPEX; keine CH-Residenz. | H6: Empfohlenes Zielnarrativ: Copilot = schneller Start; Azure = strategische Zielarchitektur; Open Source = Souveränitätsoption. Im v6-Modell wurde Copilot nicht mehr als rein cloud-native Abkürzung gerechnet, sondern für eine Hybrid-/On-Prem-Landschaft kalibriert.
B8: 2) Vergleich Kosten und Wertbeitrag der Szenarien
B9: Messgrösse | C9: Copilot Studio | D9: Azure Komp. (GPT-5.1 CH North) | E9: Open Source Azure | F9: GCP Vertex AI | G9: GCP Komponenten | H9: Kommentar
B10: Externe Personentage | C10: ='05_KOSTEN_MODELL'!C30 -> 91.375 | D10: ='05_KOSTEN_MODELL'!D30 -> 123.625 | E10: ='05_KOSTEN_MODELL'!E30 -> 129 | F10: ='05_KOSTEN_MODELL'!F30 -> 107.5 | G10: ='05_KOSTEN_MODELL'!G30 -> 118.25 | H10: Lieferaufwand extern
B11: Interne Personentage | C11: ='05_KOSTEN_MODELL'!C31 -> 34.85 | D11: ='05_KOSTEN_MODELL'!D31 -> 47.15 | E11: ='05_KOSTEN_MODELL'!E31 -> 49.2 | F11: ='05_KOSTEN_MODELL'!F31 -> 41 | G11: ='05_KOSTEN_MODELL'!G31 -> 45.1 | H11: Business-/IT-Last intern
B12: Implementierungsinvestition | C12: ='05_KOSTEN_MODELL'!C67 -> 849830 | D12: ='05_KOSTEN_MODELL'!D67 -> 1149770 | E12: ='05_KOSTEN_MODELL'!E67 -> 1199760 | F12: ='05_KOSTEN_MODELL'!F67 -> 999800 | G12: ='05_KOSTEN_MODELL'!G67 -> 1099780 | H12: Einmalige Investition
B13: Steady-state OPEX p.a. (Y4) | C13: ='05_KOSTEN_MODELL'!C70 -> 548669.63 | D13: ='05_KOSTEN_MODELL'!D70 -> 415234.36 | E13: ='05_KOSTEN_MODELL'!E70 -> 388869.03 | F13: ='05_KOSTEN_MODELL'!F70 -> 329073.66 | G13: ='05_KOSTEN_MODELL'!G70 -> 386245.33 | H13: Dauerbetrieb
B14: 5Y TCO | C14: ='05_KOSTEN_MODELL'!C69 -> 3305878.5 | D14: ='05_KOSTEN_MODELL'!D69 -> 3180398.3 | E14: ='05_KOSTEN_MODELL'!E69 -> 3134996.5 | F14: ='05_KOSTEN_MODELL'!F69 -> 2626950.9 | G14: ='05_KOSTEN_MODELL'!G69 -> 2994571.8 | H14: Investition + 5Y OPEX
B15: Konservatives Nutzenpotenzial p.a. | C15: ='07_VALUE_CASE'!C9 -> 1207439.5 | D15: ='07_VALUE_CASE'!D9 -> 1349491.2 | E15: ='07_VALUE_CASE'!E9 -> 1349491.2 | F15: ='07_VALUE_CASE'!F7 -> 1278465.3 | G15: ='07_VALUE_CASE'!G7 -> 1349491.2 | H15: Nach Szenario-Realisierung
B16: Kumulierter Nutzen über 5 Jahre | C16: ='07_VALUE_CASE'!C16 -> 4695598 | D16: ='07_VALUE_CASE'!D16 -> 5248021.3 | E16: ='07_VALUE_CASE'!E16 -> 5248021.3 | F16: ='07_VALUE_CASE'!F16 -> 4971809.6 | G16: ='07_VALUE_CASE'!G16 -> 5248021.3 | H16: Ramp-up berücksichtigt
B17: 5Y Nettowert | C17: ='07_VALUE_CASE'!C20 -> 1389719.5 | D17: ='07_VALUE_CASE'!D20 -> 2067623 | E17: ='07_VALUE_CASE'!E20 -> 2113024.8 | F17: ='07_VALUE_CASE'!F20 -> 2344858.7 | G17: ='07_VALUE_CASE'!G20 -> 2253449.4 | H17: Nutzen minus TCO
B18: Payback (Monate) | C18: ='07_VALUE_CASE'!C22 -> 15.480308 | D18: ='07_VALUE_CASE'!D22 -> 14.768145 | E18: ='07_VALUE_CASE'!E22 -> 14.987287 | F18: ='07_VALUE_CASE'!F22 -> 12.637145 | G18: ='07_VALUE_CASE'!G22 -> 13.700926 | H18: Steady-state-Payback
B20: 3) ROI Berechnung
B29: 4) Qualitative Scorecard
B30: Kriterium | C30: Copilot Studio | D30: Azure Komp. (GPT-5.1) | E30: Open Source Azure | F30: GCP Vertex AI | G30: GCP Custom | H30: Kommentar
B31: Schnelle Umsetzung | C31: ='03_SZENARIOS'!C38 -> 4 | D31: ='03_SZENARIOS'!D38 -> 4 | E31: ='03_SZENARIOS'!E38 -> 2 | F31: ='03_SZENARIOS'!F38 -> 4 | G31: ='03_SZENARIOS'!G38 -> 3 | H31: 5 = am schnellsten
B32: Flexibilität / Optimierbarkeit | C32: ='03_SZENARIOS'!C39 -> 2 | D32: ='03_SZENARIOS'!D39 -> 5 | E32: ='03_SZENARIOS'!E39 -> 5 | F32: ='03_SZENARIOS'!F39 -> 5 | G32: ='03_SZENARIOS'!G39 -> 5 | H32: 5 = am flexibelsten
B33: Integrationsfähigkeit | C33: ='03_SZENARIOS'!C40 -> 3 | D33: ='03_SZENARIOS'!D40 -> 4 | E33: ='03_SZENARIOS'!E40 -> 3 | F33: ='03_SZENARIOS'!F40 -> 4 | G33: ='03_SZENARIOS'!G40 -> 4 | H33: 5 = am einfachsten
B34: Governance / Controls | C34: ='03_SZENARIOS'!C41 -> 5 | D34: ='03_SZENARIOS'!D41 -> 4 | E34: ='03_SZENARIOS'!E41 -> 3 | F34: ='03_SZENARIOS'!F41 -> 3 | G34: ='03_SZENARIOS'!G41 -> 3 | H34: 5 = am stärksten
B35: Vendor Lock-in Risiko | C35: ='03_SZENARIOS'!C42 -> 1 | D35: ='03_SZENARIOS'!D42 -> 3 | E35: ='03_SZENARIOS'!E42 -> 5 | F35: ='03_SZENARIOS'!F42 -> 2 | G35: ='03_SZENARIOS'!G42 -> 3 | H35: 5 = niedrigstes Risiko
B36: Future-Readiness | C36: ='03_SZENARIOS'!C43 -> 2 | D36: ='03_SZENARIOS'!D43 -> 5 | E36: ='03_SZENARIOS'!E43 -> 5 | F36: ='03_SZENARIOS'!F43 -> 4 | G36: ='03_SZENARIOS'!G43 -> 5 | H36: 5 = höchste Zukunftsfähigkeit
B37: MCP-Readiness | C37: ='03_SZENARIOS'!C44 -> 2 | D37: ='03_SZENARIOS'!D44 -> 5 | E37: ='03_SZENARIOS'!E44 -> 5 | F37: ='03_SZENARIOS'!F44 -> 5 | G37: ='03_SZENARIOS'!G44 -> 5 | H37: 5 = offenste Architektur
B39: 5) Executive Empfehlung
B40: Wir empfehlen, den digitalen Assistenten auf GCP aufzubauen – mit einem schnellen Einstieg über Vertex AI und einem klaren Pfad in eine produktive Zielarchitektur. Strategischer Fit: Passt zur angestrebten LANDI / fenaco Zielarchitektur. Technisch machbar: Dynamics, SharePoint und weitere Umsysteme sind integrierbar. Ohne Sackgasse skalierbar: PoC, Pilot und produktiver Betrieb können auf derselben Plattform erfolgen. Zukunftsfähig: Mit einer offnene GCP Architektur lassen sich auch neue, unvorsehbare Entwicklungen integrieren

Sheet 02_INPUTS
B2: Integrierte Eingaben: Skalierung, Nutzung, Nutzen und kommerzielle Hebel
B4: Treiber | C4: Einheit | D4: Wert / Y1 | E4: Y2 | F4: Y3 | G4: Y4 | H4: Y5 | I4: Notiz / Quelle
B5: 1) Skalierung, Organisation und Basisgrössen
B6: Anzahl PoS | C6: Anzahl | D6: 193 | I6: Wie viele Landi Läden
B7: Anzahl Service-Mitarbeitende pro PoS | C7: Anzahl | D7: 3 | I7: Wie viele MA pro PoS
B8: Service-Center Nutzer / Mitarbeitende | C8: Anzahl | D8: 50 | I8: Anpassbar; bisherige Baseline.
B9: Zentrale Fachanwender / Experten | C9: Anzahl | D9: 25 | I9: Zusätzliche Power User.
B10: Totale potenzielle Nutzer | C10: Formel | D10: =D6*D7+D8+D9 -> 654 | I10: Formel aus Filialen und zentralen Rollen
B11: Arbeitstage pro Jahr | C11: Tage | D11: 312 | I11: Aus Landi-Annahmen
B12: Arbeitstage pro Monat | C12: Tage | D12: 21 | I12: Planungswert für Nutzungsmodell
B13: Betriebsstunden pro Tag | C13: Stunden | D13: 10 | I13: Näherungswert für Concurrency
B14: Planungshorizont | C14: Jahre | D14: 5 | I14: Standard im Modell
B15: USD/CHF Wechselkurs | C15: FX | D15: 0.8 | I15: Planungswert für Umrechnung öffentlicher USD-Preise
B17: 2) Nutzungs- und Adoptionsmodell
B18: Anteil monatlich aktiver Nutzer | C18: % Y1–Y5 | D18: 0.35 | E18: 0.6 | F18: 0.75 | G18: 0.9 | H18: 0.9 | I18: Ramp-up bis steady state
B19: Interaktionen pro aktivem Nutzer und Arbeitstag | C19: Anzahl | D19: 4 | I19: Mitarbeiter-Use-Cases in der Filiale / im SC
B20: Durchschnitt Input-Tokens pro Interaktion | C20: Token | D20: 2400 | I20: Text + Kontext
B21: Durchschnitt Output-Tokens pro Interaktion | C21: Token | D21: 500 | I21: Antwort + Begründung
B22: Anteil Bild-/Produktidentifikation | C22: % der Interaktionen | D22: 0.15 | I22: Produktidentifikation / visuelle Diagnose
B23: Zusätzliche Input-Tokens für Bildinteraktionen | C23: Token-Äquivalent | D23: 1200 | I23: Näherungswert
B24: Anteil RAG-/Retrieval-Interaktionen | C24: % der Interaktionen | D24: 0.6 | I24: Kontextzugriff auf Wissen und Systeme
B25: Anteil Interaktionen mit Aktion / Write-back | C25: % der Interaktionen | D25: 0.25 | I25: z. B. Fall vorbereiten, Lookup, Update
B26: Ablaufaktionen pro aktiver Aktionsinteraktion | C26: Anzahl | D26: 4 | I26: z. B. Connector-/Flow-Aktionen
B27: Spitzenlast-Multiplikator | C27: x | D27: 2.2 | I27: Für Peak-Token-/GPU-Dimensionierung
B29: 3) Komplexität und Kostensätze
B30: Zu integrierende Wissensquellen | C30: Anzahl | D30: 7 | I30: z. B. Knowledge Base, Blob, SharePoint
B31: Zu integrierende Kernsysteme | C31: Anzahl | D31: 6 | I31: PIM, MAM, ERP, CRM, etc.
B32: Anwendungsfälle Phase 1 | C32: Anzahl | D32: 4 | I32: Produkt identifizieren, Diagnose, Handlungsoptionen, etc.
B33: Sprachen / Märkte in Welle 1 | C33: Anzahl | D33: 2 | I33: Mehrsprachigkeit erhöht Design- und Testaufwand
B34: Sicherheits- / Compliance-Multiplikator | C34: x | D34: 1.15 | I34: Hebel auf Integrations-/Testaufwand
B35: Externer Tagessatz | C35: CHF / PD | D35: 2000 | I35: Gemischtes Delivery-Team
B36: Interner Projekt-Tagessatz | C36: CHF / PD | D36: 0 | I36: Business, IT, Security, UAT, Intern kein Kostensatz
B37: Bison Tagessatz | C37: CHF / PD | D37: =170*41/5 -> 1394 | I37: Bison Stundensatz
B38: Personalkosten Service / Filiale | C38: CHF / Stunde | D38: 50 | I38: User input
B39: Vollkostenähnlicher Satz Service / Technik | C39: CHF / Stunde | D39: 55 | I39: Für unnötige Serviceaufträge
B40: Service-Center / Admin Satz | C40: CHF / Stunde | D40: 60 | I40: Für Anfragen / Retouren / Admin
B41: Produktive Stunden pro FTE / Jahr | C41: Stunden | D41: 1800 | I41: Für FTE-Lens
B42: Monatskosten FTE Geschäft / Produkt | C42: CHF / Monat | D42: 14000 | I42: PO / Governance / Business Ownership
B43: Monatskosten FTE Plattform / Integration | C43: CHF / Monat | D43: 18000 | I43: Engineering / Integration / DevOps
B44: Monatskosten FTE Content / Wissen | C44: CHF / Monat | D44: 13000 | I44: Content Ops / Wissenspflege
B45: Contingency auf externe Plattformkosten | C45: % | D45: 0.1 | I45: Auf variable/feste Plattformkosten
B46: Hybrid- / On-Prem-Integrationsfaktor | C46: x | D46: 1.2 | I46: Erhöht Integrationsaufwand bei On-Prem-Systemen, Gateways, Netzwerk, Security und Legacy-Protokollen.
B47: 4) Nutzenannahmen: operative Effizienz
B48: Schriftliche Anfragen pro Jahr | C48: Anzahl | D48: 203875 | I48: Landi Einschätzung
B49: Service-Aufträge pro Jahr | C49: Anzahl | D49: 66225 | I49: Landi Einschätzung
B50: Retournierte Service-Aufträge pro Jahr | C50: Anzahl | D50: 50690 | I50: Landi Einschätzung
B51: Zielwert Reduktion unnötiger Service-Aufträge | C51: % | D51: 0.2 | I51: Top-down Zielwert
B52: Bearbeitungsdauer unnötiger Service-Auftrag | C52: Minuten | D52: 23 | I52: Landi Einschätzung
B53: Zeitersparnis je retournierter SA (admin) | C53: Minuten | D53: 2 | I53: Aus Landi-Nutzenannahme
B54: Override vermiedene unnötige Service-Aufträge p.a. | C54: Anzahl | D54: 13400 | I54: Aus Landi-Nutzenannahme / MT2023
B55: Override vermiedene Anfragen p.a. | C55: Anzahl | D55: 40620 | I55: Aus Landi-Nutzenannahme / MT2023
B56: Bearbeitungsdauer Anfrage heute | C56: Minuten | D56: 10 | I56: Referenz gemäss Nutzenannahme
B57: Zeitersparnis auf verbleibenden Anfragen | C57: % | D57: 0.333 | I57: 33% = 3.33 Minuten auf 10 Minuten
B58: Override verbleibende optimierte Anfragen p.a. | C58: Anzahl | D58: 162480 | I58: Aus Landi-Nutzenannahme / MT2023
B59: Direktgutschriften p.a. | C59: Anzahl | D59: 100827 | I59: Landi Einschätzung
... B64: Konservativer Wirkungsgrad Effizienz | C64: % | D64: 0.75 | I64: Basiscase
B66: 5) Nutzenannahmen: kommerzielle Hebel / Cross-Sell
B67: Ø Online Warenkorb aktuell | C67: CHF | D67: 103 | I67: Landi Einschätzung
B68: Online-Umsatz aktuell | C68: CHF | D68: 20790000 | I68: Landi Einschätzung
B69: Ø Online Warenkorb Budget 2026 | C69: CHF | D69: 104.9 | I69: Landi Einschätzung
B70: Online-Umsatz Budget 2026 | C70: CHF | D70: 23707400 | I70: Landi Einschätzung
B71: landi.ch Sitzungen aktuell p.a. | C71: CHF | D71: 25720000 | I71: Landi Einschätzung
B72: landi.ch Sitzungen Budget 2026 p.a. | C72: CHF | D72: 28250000 | I72: Landi Einschätzung
B73: Conversion Rate aktuell | C73: % | D73: 0.0078 | I73: Landi Einschätzung
B74: Conversion Rate Budget 2026 | C74: % | D74: 0.008 | I74: Landi Einschätzung
B75: Conversion Rate neu mit Assistent | C75: % | D75: 0.0085 | I75: Landi Einschätzung
B76: Totalumsatz stationär p.a. | C76: CHF | D76: 1149122000 | I76: Landi Einschätzung
B77: Marge / Deckungsbeitrag | C77: % | D77: 0.2562 | I77: Landi Einschätzung
B78: Anteil beeinflusste stationäre Verkäufe | C78: % | D78: 0 | I78: Konservativer Default; aktiv editieren falls belastbar
... B85: Umsatzsteigerung Ersatzteile p.a. | C85: % | D85: 0 | I85: Konservativer Default
B87: 6) Anzahl Dokumente
B88: PIM Export | C88: Anzahl | D88: 25385 | I88: Landi Einschätzung
B89: Produktbilder | C89: Anzahl | D89: 75379 | I89: Landi Einschätzung
B90: Ersatzteilbilder | C90: Anzahl | D90: 23150 | I90: Landi Einschätzung
B91: MAM PDF Anleitungen | C91: Anzahl | D91: 2000 | I91: Landi Einschätzung
B92: Anzahl Seiten pro PDF | C92: Anzahl | D92: 10 | I92: Schätzung Landi Website Rasentrimmer
B93: Anzahl Zeichen pro Seite | C93: Zeichen | D93: 1500 | I93: Schätzung
B94: Dateigrösse pro Seite | C94: MB | D94: 0.3 | I94: Schätzung
B95: Serviceaufträge (DWH) | C95: Zeichen | D95: 400000000 | I95: Landi Einschätzung

Sheet 03_SZENARIOS
B2: Szenariologik, Preishebel, Delivery-Aufwand und qualitative Scorecard
B3: 5 Szenarien: Copilot (100% generativ), Azure Komponenten (GPT-5.1 CH North), Open Source Azure, GCP Vertex AI, GCP Custom. 100% generative Antworten.
B4: Treiber / Hebel | C4: Copilot Studio | D4: Azure Komponenten | E4: Open Source auf Azure | F4: GCP Vertex AI | G4: GCP Komponenten | H4: Kommentar
B5: Narrativ pro Szenario
B6: Positionierung | C6: Low-Code-Plattform; 100% generative Antworten; MS verwaltet LLM (GPT-4o); Custom Connectors für MAM/Agronet nötig; keine CH-LLM-Residenz; ideal wenn 600 Nutzer bereits M365 Copilot haben. | D6: Modulare Azure-Zielarchitektur; GPT-5.1 in Switzerland North bestätigt; volle CH-Datenresidenz; maximale Kontrolle über Prompts, RAG und Integrationen; Function Calling für alle 6 Systeme. | E6: Maximale Souveränität; selbst bestimmte LLM Modelle, welche über APIs genutzt werden | F6: GCP Agent Builder + Dialogflow CX + Gemini 3.1 Pro/Flash; managed Plattform; günstige Token-Kosten; keine CH-Datenresidenz (nur EU); ideal wenn GCP strategische Plattform. | G6: GCP Custom Stack: Cloud Run + Google ADK + Gemini API direkt + Firestore Vector Search; kein Vertex AI Search Overhead ($4/1K); günstigstes all-in OPEX; keine CH-Datenresidenz (nur EU); GCP-Engineering-Expertise nötig. | H6: Diese Narrative fliessen über die Realisierungsfaktoren und die qualitative Scorecard in die Bewertung ein.
B8: 1) Operating Model / Run Model
B9: Product Owner / Backlog (FTE) | C9: 0.3 | D9: 0.35 | E9: 0.4 | F9: 0.3 | G9: 0.35 | H9: Business Ownership / Governance
B10: Wissensmanagement / Content Ops (FTE) | C10: 0.35 | D10: 0.35 | E10: 0.4 | F10: 0.35 | G10: 0.35 | H10: Kuration, Qualität, Aktualität
B11: Plattform / Integration / (Entwicklung) (FTE) | C11: 0.4 | D11: 0.5 | E11: 0.6 | F11: 0.4 | G11: 0.5 | H11: Korrigiert OSS: 0.7 FTE Plattform/Integration (war: 1.5 FTE für GPU-Cluster-Betrieb). API-basierter Betrieb eliminiert: GPU-Cluster-Management, Inference-Server-Tuning (vLLM/TGI), CUDA/Driver-Updates, Model-Weight-Management, GPU-Autoscaling. Verbleibend: Orchestrierungscode (LangGraph/SK), RAG-Pipeline-Wartung, Integrationen (PIM/MAM/ERP/CRM), Security-Patching, CI/CD, Monitoring. 0.7 FTE = leicht höher als Azure (0.6 FTE) wegen mehr Open-Source-Tooling-Verwaltung. Quelle: Marktpraxis für API-basierte GenAI-Produktivitäts-Agents, 2025.
B12: QA / Analytics / Governance (FTE) | C12: 0.2 | D12: 0.25 | E12: 0.3 | F12: 0.2 | G12: 0.25 | H12: Quality, Reporting, Guardrails
B13: Externer Support / Managed Service | C13: 2000 | D13: 2500 | E13: 1500 | F13: 1500 | G13: 1500 | H13: Copilot/Azure: MS Support Plan. GCP: Google Support. OSS: Azure Dev Support + Community-Budget.
B14: Hypercare-Aufschlag auf FTE im Jahr 1 | C14: 0.2 | D14: 0.2 | E14: 0.25 | F14: 0.2 | G14: 0.2 | H14: Temporäre Mehrbelastung im ersten Jahr
B16: 2) LLM & Modellkosten / Plattform & Infrastrukturkosten
B17: LLM & ModellKosten (variable)
B18: Token Input-Preis (CHF / 1 Mio. Tokens) | C18: Credits → | D18: 2.5 | E18: 0.5 | F18: 1 | G18: 2 | H18: CHF/1M Input-Tokens. Copilot: Credits-Modell (keine Token-Preise). Azure berechnet mit GPT 5.4 / GPC Gemini 3.1 Pro
B19: Token Output-Preis (CHF / 1 Mio. Tokens) | C19: Credits → | D19: 15 | E19: 3 | F19: 6 | G19: 12 | H19: GCP Vertex: blended Gemini Flash 50%/Pro 50%. Azure: GPT-5.4 $15/M Out. OSS: Llama 4 (Foundry).
B20: Ø Copilot Credits / Interaktion | C20: 10 | D20: ← gilt für alle Szenarien | H20: 1 gen. Antwort (2) + 1.5 Agent Actions × 5 (7.5) + 0.1 AI-Tools × 1.5 (0.15)
B21: Copilot Credit-Preis (CHF / Credit, Capacity Pack) | C21: 0.0088 | D21: ← gilt für alle Szenarien | H21: USD 200 / 25'000 Credits × FX 0.80. PAYG = CHF 0.008.
B22: Plattform & Infrastruktur (montalich, fix) | C22: =SUM(C23:C34) -> 825 | D22: =SUM(D23:D34) -> 4137.1 | E22: =SUM(E23:E34) -> 1172.6 | F22: =SUM(F23:F34) -> 3206.5 | G22: =SUM(G23:G34) -> 3404.5
B23: Suche / RAG (Vector Search) | C23: 0 | D23: 1100 | E23: 245 | F23: 1250 | G23: 1250 | H23: Copilot: in Credits enthalten. GCP-V: Vertex AI Search ($4/1K, 103K Queries/Jahr). Azure: AI Search S1 2 SU. OSS: AI Search S1 1 SU. GCP-C: Firestore (nahezu gratis).
B24: API Gateway / Orchestrierung / Compute | C24: — | D24: 2300 | E24: 450 | F24: 1500 | G24: 1500 | H24: Copilot: Azure: APIM CHF 650 + Container Apps CHF 1'200. OSS: Container Apps CHF 450. GCP: Cloud Run ~CHF 150.
B25: Sessions / Dialogflow | C25: — | D25: — | E25: — | F25: 120 | G25: — | H25: GCP Vertex: Dialogflow CX $0.007/Session × 18'000 = ~CHF 120/Monat.
B26: State / Session Cache (Redis/Memorystore) | C26: — | D26: 180 | E26: 90 | F26: — | G26: 40 | H26: Azure: Redis C2 (6GB HA) CHF 180. OSS: Redis C1 (1GB) CHF 90. GCP Custom: Memorystore Basic CHF 40.
B27: Datenbank (Conversation History / State) | C27: — | D27: 30 | E27: 30 | F27: — | G27: 20 | H27: Azure & OSS: CosmosDB Serverless ~CHF 30. GCP Custom: Firestore CHF 20.
B28: Monitoring / Logging | C28: — | D28: 130 | E28: 70 | F28: 20 | G28: 20 | H28: Azure: Log Analytics ~55GB/Mt × $2.30/GB = CHF 130. GCP: Cloud Logging CHF 20. OSS: Log Analytics CHF 70.
B29: Storage (Dokumente, Backups, Registry) | C29: — | D29: 16 | E29: 16 | F29: 15 | G29: 15 | H29: Azure: Blob Hot 350GB = CHF 6 + Container Registry CHF 5 + Backups CHF 5. GCP: Cloud Storage CHF 15.
B30: Secrets / Key Management | C30: — | D30: 5 | E30: 5 | F30: — | G30: — | H30: Azure: Key Vault Standard CHF 5.
B31: Security / DDoS (Cloud Armor / API Shield) | C31: — | D31: — | E31: — | F31: 10 | G31: 10 | H31: GCP: Cloud Armor CHF 10.
B32: Custom Connector Hosting (für MAM/Agronet) | C32: 200 | D32: — | E32: — | F32: — | G32: — | H32: Copilot: SixOMC MAM & Agronet nicht als Standard-Power-Platform-Connector verfügbar.
B33: Basis-Plattform / Monat (paketiert / OSS) | C33: 550 | D33: 0 | E33: 160 | F33: 0 | G33: 240 | H33: Copilot: CHF 550/Mt (Power Platform). Azure: 0. OSS: 0.
B34: Contingency (10–12%) | C34: =SUM(C23:C33)*0.1 -> 75 | D34: =SUM(D23:D33)*0.1 -> 376.1 | E34: =SUM(E23:E33)*0.1 -> 106.6 | F34: =SUM(F23:F33)*0.1 -> 291.5 | G34: =SUM(G23:G33)*0.1 -> 309.5 | H34: Puffer für Preisänderungen, Lastspitzen, unvorhergesehene Kosten.
B37: 3) Qualitative Scorecard und Nutzen-Realisierung
B38: Schnelle Umsetzung bis Marktreife (1–5) | C38: 4 | D38: 4 | E38: 2 | F38: 4 | G38: 3 | H38: 5 = schnellste Time-to-Value
B39: Flexibilität / Optimierbarkeit (1–5) | C39: 2 | D39: 5 | E39: 5 | F39: 5 | G39: 5 | H39: 5 = höchste Tiefe / Modularität
B40: Integrationsfähigkeit (1–5) | C40: 3 | D40: 4 | E40: 3 | F40: 4 | G40: 4 | H40: Bei Hybrid-/On-Prem-Landschaft ist Copilot integrativ nicht mehr klar einfacher als Azure-Komponenten.
B41: Governance / Controls (1–5) | C41: 5 | D41: 4 | E41: 3 | F41: 3 | G41: 3 | H41: 5 = stärkste Governance
B42: Vendor Lock-in Risiko (1–5) | C42: 1 | D42: 3 | E42: 5 | F42: 2 | G42: 3 | H42: 5 = niedrigstes Lock-in-Risiko
B43: Future-Readiness / modulare Architektur (1–5) | C43: 2 | D43: 5 | E43: 5 | F43: 4 | G43: 5 | H43: 5 = höchste Zukunftsfähigkeit
B44: MCP-Readiness / Offenheit (1–5) | C44: 2 | D44: 5 | E44: 5 | F44: 5 | G44: 5 | H44: 5 = höchste Offenheit
B45: Realisierungsfaktor Effizienznutzen | C45: 0.85 | D45: 0.95 | E45: 0.95 | F45: 0.9 | G45: 0.95 | H45: Zukunftsfähigkeit und Abhängigkeitshebel
B46: Realisierungsfaktor kommerzielle Upside | C46: 0.45 | D46: 0.85 | E46: 0.9 | F46: 0.7 | G46: 0.85 | H46: Tiefere Integration erhöht kommerzielles Potenzial

Sheet 04_PoC_MVP_Phasen
B2: Die Berechnungen sind aktuell auf externen Tagessätzen basierend ausgeführt
B4: PHASE 1 – PoC (Proof of Concept)
B5: Ziel: Technologie validieren in 6–8 Wochen. Kein Live-Systemzugriff – statische Daten und Uploads. 4 Use Cases vollständig gebaut und von SMEs bewertet. Go/No-Go Entscheid für MVP.
B6: Use Cases: UC1: Produkt identifizieren · UC2: Produktinfos bereitstellen · UC3: Diagnose · UC4: Handlungsoptionen
B7: Aufgabe / Deliverable | C7: Wochen | D7: Projektleitung / Delivery Lead | E7: Fachlead / Product Owner Landi | F7: Key User / SMEs Landi | G7: Solution Architect / Lead Engineer | H7: AI Engineer / Data Scientist | I7: Data Engineer | J7: Business Analyst / Quality Assurance | K7: Total PT | L7: Ext. Kosten CHF
B8: P0 Projektsteup PoC und PMO | C8: =ROUNDUP(MAX(D8:J8)/5,0) -> 1 | D8: =SUMIFS($T$73:$T$131,$P$73:$P$131,LEFT($B8,2),$R$73:$R$131,D$7) -> 5 | E8: =SUMIFS($T$73:$T$131,$P$73:$P$131,LEFT($B8,2),$R$73:$R$131,E$7) -> 1 | F8: =SUMIFS($T$73:$T$131,$P$73:$P$131,LEFT($B8,2),$R$73:$R$131,F$7) -> 1 | G8: =SUMIFS($T$73:$T$131,$P$73:$P$131,LEFT($B8,2),$R$73:$R$131,G$7) -> 0 | H8: =SUMIFS($T$73:$T$131,$P$73:$P$131,LEFT($B8,2),$R$73:$R$131,H$7) -> 0 | I8: =SUMIFS($T$73:$T$131,$P$73:$P$131,LEFT($B8,2),$R$73:$R$131,I$7) -> 0 | J8: =SUMIFS($T$73:$T$131,$P$73:$P$131,LEFT($B8,2),$R$73:$R$131,J$7) -> 0 | K8: =SUM(D8:J8) -> 7 | L8: =SUM(D8,G8,H8,I8,J8)*'02_INPUTS'!$D$35 -> 10000
B9: P1 Ground Truth & Kalibrierung | C9: =ROUNDUP(MAX(D9:J9)/5,0) -> 2 | D9: =SUMIFS($T$73:$T$131,$P$73:$P$131,LEFT($B9,2),$R$73:$R$131,D$7) -> 2 | E9: =SUMIFS($T$73:$T$131,$P$73:$P$131,LEFT($B9,2),$R$73:$R$131,E$7) -> 4 | F9: =SUMIFS($T$73:$T$131,$P$73:$P$131,LEFT($B9,2),$R$73:$R$131,F$7) -> 10 | G9: =SUMIFS($T$73:$T$131,$P$73:$P$131,LEFT($B9,2),$R$73:$R$131,G$7) -> 1 | H9: =SUMIFS($T$73:$T$131,$P$73:$P$131,LEFT($B9,2),$R$73:$R$131,H$7) -> 0.5 | I9: =SUMIFS($T$73:$T$131,$P$73:$P$131,LEFT($B9,2),$R$73:$R$131,I$7) -> 0.5 | J9: =SUMIFS($T$73:$T$131,$P$73:$P$131,LEFT($B9,2),$R$73:$R$131,J$7) -> 5 | K9: =SUM(D9:J9) -> 23 | L9: =SUM(D9,G9,H9,I9,J9)*'02_INPUTS'!$D$35 -> 18000
B10: P2 Detaildesign & Datenvorbereitung | C10: =ROUNDUP(MAX(D10:J10)/5,0) -> 1 | D10: =SUMIFS($T$73:$T$131,$P$73:$P$131,LEFT($B10,2),$R$73:$R$131,D$7) -> 1 | E10: =SUMIFS($T$73:$T$131,$P$73:$P$131,LEFT($B10,2),$R$73:$R$131,E$7) -> 2 | F10: =SUMIFS($T$73:$T$131,$P$73:$P$131,LEFT($B10,2),$R$73:$R$131,F$7) -> 2 | G10: =SUMIFS($T$73:$T$131,$P$73:$P$131,LEFT($B10,2),$R$73:$R$131,G$7) -> 3 | H10: =SUMIFS($T$73:$T$131,$P$73:$P$131,LEFT($B10,2),$R$73:$R$131,H$7) -> 3.5 | I10: =SUMIFS($T$73:$T$131,$P$73:$P$131,LEFT($B10,2),$R$73:$R$131,I$7) -> 3 | J10: =SUMIFS($T$73:$T$131,$P$73:$P$131,LEFT($B10,2),$R$73:$R$131,J$7) -> 1.5 | K10: =SUM(D10:J10) -> 16 | L10: =SUM(D10,G10,H10,I10,J10)*'02_INPUTS'!$D$35 -> 24000
B11: P3 Runtime & Basisplattform | C11: =ROUNDUP(MAX(D11:J11)/5,0) -> 2 | D11: =SUMIFS($T$73:$T$131,$P$73:$P$131,LEFT($B11,2),$R$73:$R$131,D$7) -> 0.5 | E11: =SUMIFS($T$73:$T$131,$P$73:$P$131,LEFT($B11,2),$R$73:$R$131,E$7) -> 0.5 | F11: =SUMIFS($T$73:$T$131,$P$73:$P$131,LEFT($B11,2),$R$73:$R$131,F$7) -> 0.5 | G11: =SUMIFS($T$73:$T$131,$P$73:$P$131,LEFT($B11,2),$R$73:$R$131,G$7) -> 2 | H11: =SUMIFS($T$73:$T$131,$P$73:$P$131,LEFT($B11,2),$R$73:$R$131,H$7) -> 6.5 | I11: =SUMIFS($T$73:$T$131,$P$73:$P$131,LEFT($B11,2),$R$73:$R$131,I$7) -> 1.5 | J11: =SUMIFS($T$73:$T$131,$P$73:$P$131,LEFT($B11,2),$R$73:$R$131,J$7) -> 1.5 | K11: =SUM(D11:J11) -> 13 | L11: =SUM(D11,G11,H11,I11,J11)*'02_INPUTS'!$D$35 -> 24000
B12: P4 Agenten-Implementierung | C12: =ROUNDUP(MAX(D12:J12)/5,0) -> 4 | D12: =SUMIFS($T$73:$T$131,$P$73:$P$131,LEFT($B12,2),$R$73:$R$131,D$7) -> 10 | E12: =SUMIFS($T$73:$T$131,$P$73:$P$131,LEFT($B12,2),$R$73:$R$131,E$7) -> 4 | F12: =SUMIFS($T$73:$T$131,$P$73:$P$131,LEFT($B12,2),$R$73:$R$131,F$7) -> 4 | G12: =SUMIFS($T$73:$T$131,$P$73:$P$131,LEFT($B12,2),$R$73:$R$131,G$7) -> 3 | H12: =SUMIFS($T$73:$T$131,$P$73:$P$131,LEFT($B12,2),$R$73:$R$131,H$7) -> 16.5 | I12: =SUMIFS($T$73:$T$131,$P$73:$P$131,LEFT($B12,2),$R$73:$R$131,I$7) -> 4 | J12: =SUMIFS($T$73:$T$131,$P$73:$P$131,LEFT($B12,2),$R$73:$R$131,J$7) -> 6 | K12: =SUM(D12:J12) -> 47.5 | L12: =SUM(D12,G12,H12,I12,J12)*'02_INPUTS'!$D$35 -> 79000
B13: UC1: Produkt identifizieren
B14: UC2: Produktinformationen bereitstellen | V14: 40000
B15: UC3: Diagnose stellen | V15: 27000
B16: UC4: Handlungsoptionen | V16: 22000
B17: P5 Validierung & Tuning | C17: =ROUNDUP(MAX(D17:J17)/5,0) -> 2 | D17: =SUMIFS($T$73:$T$131,$P$73:$P$131,LEFT($B17,2),$R$73:$R$131,D$7) -> 5 | E17: =SUMIFS($T$73:$T$131,$P$73:$P$131,LEFT($B17,2),$R$73:$R$131,E$7) -> 3 | F17: =SUMIFS($T$73:$T$131,$P$73:$P$131,LEFT($B17,2),$R$73:$R$131,F$7) -> 6 | G17: =SUMIFS($T$73:$T$131,$P$73:$P$131,LEFT($B17,2),$R$73:$R$131,G$7) -> 2 | H17: =SUMIFS($T$73:$T$131,$P$73:$P$131,LEFT($B17,2),$R$73:$R$131,H$7) -> 9 | I17: =SUMIFS($T$73:$T$131,$P$73:$P$131,LEFT($B17,2),$R$73:$R$131,I$7) -> 1.5 | J17: =SUMIFS($T$73:$T$131,$P$73:$P$131,LEFT($B17,2),$R$73:$R$131,J$7) -> 4.5 | K17: =SUM(D17:J17) -> 31 | L17: =SUM(D17,G17,H17,I17,J17)*'02_INPUTS'!$D$35 -> 44000 | V17: 80000
B18: RAGAS-Metriken, SME-Review, Gap-Liste | V18: 52000
B19: P6 Abschluss & MVP-Entscheid | C19: =ROUNDUP(MAX(D19:J19)/5,0) -> 1 | D19: =SUMIFS($T$73:$T$131,$P$73:$P$131,LEFT($B19,2),$R$73:$R$131,D$7) -> 1 | E19: =SUMIFS($T$73:$T$131,$P$73:$P$131,LEFT($B19,2),$R$73:$R$131,E$7) -> 0.5 | F19: =SUMIFS($T$73:$T$131,$P$73:$P$131,LEFT($B19,2),$R$73:$R$131,F$7) -> 0.5 | G19: =SUMIFS($T$73:$T$131,$P$73:$P$131,LEFT($B19,2),$R$73:$R$131,G$7) -> 1 | H19: =SUMIFS($T$73:$T$131,$P$73:$P$131,LEFT($B19,2),$R$73:$R$131,H$7) -> 2 | I19: =SUMIFS($T$73:$T$131,$P$73:$P$131,LEFT($B19,2),$R$73:$R$131,I$7) -> 0.5 | J19: =SUMIFS($T$73:$T$131,$P$73:$P$131,LEFT($B19,2),$R$73:$R$131,J$7) -> 0.5 | K19: =SUM(D19:J19) -> 6 | L19: =SUM(D19,G19,H19,I19,J19)*'02_INPUTS'!$D$35 -> 10000 | V19: 10000
B20: P7 PoC-Dokumentation & Go/No-Go Vorlage | C20: =ROUNDUP(MAX(D20:J20)/5,0) -> 1 | D20: =SUMIFS($T$73:$T$131,$P$73:$P$131,LEFT($B20,2),$R$73:$R$131,D$7) -> 3 | E20: =SUMIFS($T$73:$T$131,$P$73:$P$131,LEFT($B20,2),$R$73:$R$131,E$7) -> 2 | F20: =SUMIFS($T$73:$T$131,$P$73:$P$131,LEFT($B20,2),$R$73:$R$131,F$7) -> 0 | G20: =SUMIFS($T$73:$T$131,$P$73:$P$131,LEFT($B20,2),$R$73:$R$131,G$7) -> 0 | H20: =SUMIFS($T$73:$T$131,$P$73:$P$131,LEFT($B20,2),$R$73:$R$131,H$7) -> 0 | I20: =SUMIFS($T$73:$T$131,$P$73:$P$131,LEFT($B20,2),$R$73:$R$131,I$7) -> 0 | J20: =SUMIFS($T$73:$T$131,$P$73:$P$131,LEFT($B20,2),$R$73:$R$131,J$7) -> 0 | K20: =SUM(D20:J20) -> 5 | L20: =SUM(D20,G20,H20,I20,J20)*'02_INPUTS'!$D$35 -> 6000 | V20: 20’000
B21: Einmahlige Software / Entwicklung Gebühr | L21: 35000 | V21: =SUM(V14:V20) -> 231000
B22: PHASE TOTAL | D22: =SUM(D17:D20,D8:D12) -> 27.5 | E22: =SUM(E17:E20,E8:E12) -> 17 | F22: =SUM(F17:F20,F8:F12) -> 24 | G22: =SUM(G17:G20,G8:G12) -> 12 | H22: =SUM(H17:H20,H8:H12) -> 38 | I22: =SUM(I17:I20,I8:I12) -> 11 | J22: =SUM(J17:J20,J8:J12) -> 19 | K22: =SUM(D22:J22) -> 148.5 | L22: =SUM(L8:L21) -> 250000
B23: Externe PT: 56 PT · Ext. Kosten CHF 2'000/PT: CHF 112,000 · SME intern: 17 PT · Total PT: 73 PT
B26: PHASE 2 – MVP (Minimum Viable Product)
B27: Ziel: Alle 8 Use Cases produktionsreif in 14–18 Wochen. 6 Live-Integrationen (PIM, MAM, ERP, Agronet, Odoo, SharePoint). Security-Audit, End-to-End-Testing, Rollout auf 600 Nutzer.
B28: Use Cases: UC1: Produkt identifizieren · UC2: Produktinfos bereitstellen · UC3: Diagnose · UC4: Handlungsoptionen · UC5: Ersatzteil · UC6: Garantie · UC7: Case vorbereiten · UC8: Dokumentation
B29: Aufgabe / Deliverable | C29: Wochen | D29: Projektleitung / Delivery Lead | E29: Fachlead / Product Owner Landi | F29: Key User / SMEs Landi | G29: Solution Architect / Cloud Engineer | H29: AI Engineer / Data Scientist | I29: Data Engineer | J29: Business Analyst / Quality Assurance | K29: Total PT | L29: Ext. Kosten CHF
B30: ── Projektstart und Organisation ────── | L30: =SUM(L31:L34) -> 190800
B31: Architektur & Security Design | C31: =ROUNDUP(MAX(D31:J31)/5,0) -> 1 | D31: 5 | E31: 2 | F31: 2 | G31: 2 | H31: 2 | I31: 0 | J31: 0 | K31: =SUM(C31:J31) -> 14 | L31: =SUM(D31,G31,H31,I31,J31)*'02_INPUTS'!$D$35 -> 18000
B32: CH-Residenz, IAM, Netzwerk, Audit-Log | C32: =ROUNDUP(MAX(D32:J32)/5,0) -> 1 | D32: 2 | E32: 1 | F32: 1 | G32: 1 | H32: 0 | I32: 0 | J32: 0 | K32: =SUM(C32:J32) -> 6 | L32: =SUM(D32,G32,H32,I32,J32)*'02_INPUTS'!$D$35 -> 6000
B33: Szenario GCP Vertex zu GCP Migration | C33: =ROUNDUP(MAX(D33:J33)/5,0) -> 2 | D33: 5 | E33: 0 | F33: 0 | G33: 10 | H33: 5 | I33: 10 | J33: 5 | K33: =SUM(C33:J33) -> 37 | L33: =SUM(D33,G33,H33,I33,J33)*'02_INPUTS'!$D$35 -> 70000
B34: Projektarbeit, Abstimmung und Kommunikation | C34: =ROUNDUP(MAX(D34:J34)/5,0) -> 3 | D34: =SUM(D36:D55)*0.2 -> 8.6 | E34: =SUM(E36:E55)*0.2 -> 9.8 | F34: =SUM(F36:F55)*0.2 -> 9.2 | G34: =SUM(G36:G55)*0.2 -> 13.6 | H34: =SUM(H36:H55)*0.2 -> 10.2 | I34: =SUM(I36:I55)*0.2 -> 9.4 | J34: =SUM(J36:J55)*0.2 -> 6.6 | K34: =SUM(D34:J34) -> 67.4 | L34: =SUM(D34,G34,H34,I34,J34)*'02_INPUTS'!$D$35 -> 96800
B35: ── INTEGRATIONEN ─────────────── | C35: =ROUNDUP(MAX(D35:J35)/5,0) -> 0 | D35: 0 | E35: 0 | F35: 0 | G35: 0 | H35: 0 | I35: 0 | K35: =SUM(C35:J35) -> 0 | L35: =SUM(L36:L41) -> 118000
B36: Integration: PIM – Elytra (Produktdaten) | C36: =ROUNDUP(MAX(D36:J36)/5,0) -> 2 | D36: 1 | E36: 2 | F36: 6 | G36: 5 | H36: 2 | I36: 2 | J36: 0 | K36: =SUM(C36:J36) -> 20 | L36: =SUM(D36,G36,H36,I36,J36)*'02_INPUTS'!$D$35 -> 20000
B37: Integration: MAM – SixOMC (Assets/Bilder) | C37: =ROUNDUP(MAX(D37:J37)/5,0) -> 1 | D37: 1 | E37: 2 | F37: 5 | G37: 5 | H37: 2 | I37: 2 | J37: 0 | K37: =SUM(C37:J37) -> 18 | L37: =SUM(D37,G37,H37,I37,J37)*'02_INPUTS'!$D$35 -> 20000
B38: Integration: ERP – B4LCH (Garantie/Auftr.) | C38: =ROUNDUP(MAX(D38:J38)/5,0) -> 2 | D38: 1 | E38: 3 | F38: 8 | G38: 5 | H38: 2 | I38: 3 | J38: 0 | K38: =SUM(C38:J38) -> 24 | L38: =SUM(D38,G38,H38,I38,J38)*'02_INPUTS'!$D$35 -> 22000
B39: Integration: Agronet (Middleware) | C39: =ROUNDUP(MAX(D39:J39)/5,0) -> 2 | D39: 1 | E39: 2 | F39: 6 | G39: 5 | H39: 2 | I39: 2 | J39: 0 | K39: =SUM(C39:J39) -> 20 | L39: =SUM(D39,G39,H39,I39,J39)*'02_INPUTS'!$D$35 -> 20000
B40: Integration: Odoo (Endkundenstamm) | C40: =ROUNDUP(MAX(D40:J40)/5,0) -> 1 | D40: 1 | E40: 1 | F40: 3 | G40: 5 | H40: 2 | I40: 1 | J40: 0 | K40: =SUM(C40:J40) -> 14 | L40: =SUM(D40,G40,H40,I40,J40)*'02_INPUTS'!$D$35 -> 18000
B41: Integration: SharePoint (erweitert) | C41: =ROUNDUP(MAX(D41:J41)/5,0) -> 1 | D41: 1 | E41: 1 | F41: 2 | G41: 5 | H41: 2 | I41: 1 | J41: 0 | K41: =SUM(C41:J41) -> 13 | L41: =SUM(D41,G41,H41,I41,J41)*'02_INPUTS'!$D$35 -> 18000
B42: ── USE CASES ─────────────────── | C42: =ROUNDUP(MAX(D42:J42)/5,0) -> 0 | D42: 0 | E42: 0 | F42: 0 | G42: 0 | H42: 0 | I42: 0 | K42: =SUM(C42:J42) -> 0 | L42: =SUM(L43:L50) -> 242000
B43: UC1: Produkt identifizieren | C43: =ROUNDUP(MAX(D43:J43)/5,0) -> 1 | D43: 3 | E43: 3 | F43: 1 | G43: 2 | H43: 4 | I43: 3 | J43: 2 | K43: =SUM(C43:J43) -> 19 | L43: =SUM(D43,G43,H43,I43,J43)*'02_INPUTS'!$D$35 -> 28000
B44: UC2: Produktinfos bereitstellen | C44: =ROUNDUP(MAX(D44:J44)/5,0) -> 1 | D44: 3 | E44: 3 | F44: 1 | G44: 2 | H44: 4 | I44: 3 | J44: 2 | K44: =SUM(C44:J44) -> 19 | L44: =SUM(D44,G44,H44,I44,J44)*'02_INPUTS'!$D$35 -> 28000
B45: UC3: Diagnose durchführen | C45: =ROUNDUP(MAX(D45:J45)/5,0) -> 2 | D45: 6 | E45: 6 | F45: 2 | G45: 4 | H45: 4 | I45: 5 | J45: 2 | K45: =SUM(C45:J45) -> 31 | L45: =SUM(D45,G45,H45,I45,J45)*'02_INPUTS'!$D$35 -> 42000
B46: UC4: Handlungsoptionen empfehlen | C46: =ROUNDUP(MAX(D46:J46)/5,0) -> 1 | D46: 4 | E46: 4 | F46: 1 | G46: 3 | H46: 4 | I46: 3 | J46: 2 | K46: =SUM(C46:J46) -> 22 | L46: =SUM(D46,G46,H46,I46,J46)*'02_INPUTS'!$D$35 -> 32000
B47: UC5: Ersatzteil identifizieren | C47: =ROUNDUP(MAX(D47:J47)/5,0) -> 1 | D47: 4 | E47: 4 | F47: 2 | G47: 2 | H47: 4 | I47: 3 | J47: 2 | K47: =SUM(C47:J47) -> 22 | L47: =SUM(D47,G47,H47,I47,J47)*'02_INPUTS'!$D$35 -> 30000
B48: UC6: Garantie prüfen (ERP Live) | C48: =ROUNDUP(MAX(D48:J48)/5,0) -> 1 | D48: 3 | E48: 3 | F48: 2 | G48: 2 | H48: 4 | I48: 3 | J48: 2 | K48: =SUM(C48:J48) -> 20 | L48: =SUM(D48,G48,H48,I48,J48)*'02_INPUTS'!$D$35 -> 28000
B49: UC7: Anfrage (Case) vorbereiten | C49: =ROUNDUP(MAX(D49:J49)/5,0) -> 1 | D49: 3 | E49: 3 | F49: 1 | G49: 3 | H49: 4 | I49: 2 | J49: 2 | K49: =SUM(C49:J49) -> 19 | L49: =SUM(D49,G49,H49,I49,J49)*'02_INPUTS'!$D$35 -> 28000
B50: UC8: Dokumentation optimieren | C50: =ROUNDUP(MAX(D50:J50)/5,0) -> 1 | D50: 2 | E50: 2 | F50: 1 | G50: 3 | H50: 4 | I50: 2 | J50: 2 | K50: =SUM(C50:J50) -> 17 | L50: =SUM(D50,G50,H50,I50,J50)*'02_INPUTS'!$D$35 -> 26000
B51: ── ABSCHLUSS ─────────────────── | C51: =ROUNDUP(MAX(D51:J51)/5,0) -> 0 | D51: 0 | E51: 0 | F51: 0 | G51: 0 | H51: 0 | I51: 0 | K51: =SUM(C51:J51) -> 0 | L51: =SUM(L52:L57) -> 234000
B52: Security Audit & Compliance Abnahme | C52: =ROUNDUP(MAX(D52:J52)/5,0) -> 1 | D52: 3 | E52: 2 | F52: 1 | G52: 3 | H52: 1 | I52: 1 | J52: 0 | K52: =SUM(C52:J52) -> 12 | L52: =SUM(D52,G52,H52,I52,J52)*'02_INPUTS'!$D$35 -> 16000
B53: E2E-Testing & Evaluation (alle 8 UCs) | C53: =ROUNDUP(MAX(D53:J53)/5,0) -> 2 | D53: 1 | E53: 5 | F53: 2 | G53: 4 | H53: 1 | I53: 6 | J53: 5 | K53: =SUM(C53:J53) -> 26 | L53: =SUM(D53,G53,H53,I53,J53)*'02_INPUTS'!$D$35 -> 34000
B54: Betriebskonzept vor dem Rollout | C54: =ROUNDUP(MAX(D54:J54)/5,0) -> 2 | D54: 4 | E54: 2 | F54: 2 | G54: 6 | H54: 2 | I54: 2 | J54: 4 | K54: =SUM(C54:J54) -> 24 | L54: =SUM(D54,G54,H54,I54,J54)*'02_INPUTS'!$D$35 -> 36000
B55: Rollout & Training (600 Nutzer) | C55: =ROUNDUP(MAX(D55:J55)/5,0) -> 2 | D55: 1 | E55: 1 | F55: 0 | G55: 4 | H55: 3 | I55: 3 | J55: 8 | K55: =SUM(C55:J55) -> 22 | L55: =SUM(D55,G55,H55,I55,J55)*'02_INPUTS'!$D$35 -> 38000
B56: PMO / Steuerung / Risikomanagement | C56: =ROUNDUP(MAX(D56:J56)/5,0) -> 2 | D56: 10 | E56: 10 | F56: 0 | G56: 2 | H56: 8 | I56: 0 | J56: 0 | K56: =SUM(C56:J56) -> 32 | L56: =SUM(D56,G56,H56,I56,J56)*'02_INPUTS'!$D$35 -> 40000
B57: Einmahlige Software / Entwicklung Gebühr | L57: 70000
B58: PHASE TOTAL | D58: =SUM(D31:D56) -> 73.6 | E58: =SUM(E31:E56) -> 71.8 | F58: =SUM(F31:F56) -> 58.2 | G58: =SUM(G31:G56) -> 96.6 | H58: =SUM(H31:H56) -> 76.2 | I58: =SUM(I31:I56) -> 66.4 | J58: =SUM(J31:J56) -> 44.6 | K58: =SUM(K31:K56) -> 518.4 | L58: =SUM(L31:L34,L36:L41,L43:L50,L52:L57) -> 784800
B59: Externe PT: 162 PT · Ext. Kosten CHF 2'000/PT: CHF 324,000 · SME intern: 39 PT · Total PT: 201 PT
B62: Szenario-Aufschläge auf externe PT
B63: Szenario | C63: Aufschlag ext. PT | D63: Kostenfaktor | E63: Begründung
B64: ① Copilot Studio | C64: –15% | D64: 0.85 | E64: Low-Code: Weniger Entwicklungs-Aufwand.
B65: ② GCP Vertex AI | C65: ±0% | D65: 1 | E65: Basis-Kalkulation gilt direkt.
B66: ③ Azure GPT-5.1 | C66: +15% | D66: 1.15 | E66: Custom Orchestrierung, Function Calling vollständig custom, Azure AI Search Setup
B67: ④ OSS Azure (Llama 4) | C67: +20% | D67: 1.2 | E67: Zusätzlich Modell-Evaluation, OSS-Stack-Integration.
B68: ⑤ GCP Komponenten (ADK) | C68: +10% | D68: 1.1 | E68: ADK noch jung; Firestore-Vektor-Setup extra.
P72: Phase_ID | Q72: Phase | R72: Rolle | S72: Owner | T72: PT_in_Phase | U72: Wochen | V72: Phasenfokus | W72: Rollenfokus_in_Phase | X72: Exakte_Deliverables | Y72: Abnahmekriterium
P73: P0 | Q73: Projekt Setup | R73: Projektleitung / Delivery Lead | S73: Zühlke | T73: 5 | U73: W0 | V73: Aufsetzen des PoC Projekt / Stakeholder alignment | W73: Aufsetzen des PoC Projekt / Stakeholder alignment | X73: Projektplan, Stakholder map, Governance Strukturen | Y73: Projektplan und Governance erstellt
P74: P0 | Q74: Projekt Setup | R74: Fachlead / Product Owner Landi | S74: Landi / Zühlke | T74: 1 | U74: W0 | V74: Aufsetzen des PoC Projekt / Stakeholder alignment | W74: Aufsetzen des PoC Projekt / Stakeholder alignment | X74: Inputs für die Projektphase + Review
P75: P0 | Q75: Projekt Setup | R75: Key User / SMEs Landi | S75: Landi | T75: 1 | U75: W0 | V75: Erste Inputs und Abstimmung zur Nutzung | W75: Erste Inputs und Abstimmung zur Nutzung | X75: Inputs zu Nutzung
P76: P1 | Q76: Ground Truth & Kalibrierung | R76: AI Engineer / Data Scientist | S76: Zuehlke | T76: 0.5 | U76: W1, W2 | V76: Ground Truth erheben, labeln, konsolidieren und Abnahmekriterien fixieren | W76: Evaluationslogik fuer Agenten-/LLM-Outputs und Output-Schema frueh definieren | X76: Vorschlag fuer Ergebnis-Schema; erste Bewertungsmetriken (Trefferquote, Regelverstoss, Erklaerbarkeit); Auswertungskriterien fuer den PoC | Y76: Output-Schema und Messlogik abgestimmt
P77: P1 | Q77: Ground Truth & Kalibrierung | R77: AI Engineer / Data Scientist | S77: Zuehlke | T77: 0 | U77: W1 | V77: Ground Truth erheben, labeln, konsolidieren und Abnahmekriterien fixieren | W77: Technische Erfassungs- und Review-Mechanik fuer Annotation und spaeteres Logging vorbereiten | X77: Skizze fuer Review-/Annotation-Workflow; Logging-Anforderungen; technische Liste benoetigter Plattform-Bausteine | Y77: Technische Review-/Logging-Anforderungen abgestimmt
P78: P1 | Q78: Ground Truth & Kalibrierung | R78: Business Analyst / Quality Assurance | S78: Zuehlke | T78: 3 | U78: W1, W2 | V78: Ground Truth erheben, labeln, konsolidieren und Abnahmekriterien fixieren | W78: Falltemplate, Annotationstemplates und Entscheidungspfad aus Business-Sicht strukturieren | X78: Falltemplate; Annotation-Template; Entscheidungsbaum fuer Referenzfaelle; offener Fragenkatalog | Y78: Templates von Fachlead und SMEs akzeptiert
P79: P1 | Q79: Ground Truth & Kalibrierung | R79: Data Engineer | S79: Zuehlke | T79: 0.5 | U79: W1, W2 | V79: Ground Truth erheben, labeln, konsolidieren und Abnahmekriterien fixieren | W79: Datenstichprobe und Verfuegbarkeit der fuer die Ground Truth benoetigten Attribute absichern | X79: Sample-Export; Attributinventar; Verfuegbarkeits- und Vollstaendigkeitsuebersicht; erste Datenqualitaetsnotizen | Y79: Benötigte Felder fuer Referenzfallset verifiziert
P80: P1 | Q80: Ground Truth & Kalibrierung | R80: Fachlead / Product Owner Landi | S80: Landi | T80: 4 | U80: W1, W2 | V80: Ground Truth erheben, labeln, konsolidieren und Abnahmekriterien fixieren | W80: Fachliche Zielentscheidung, Bewertungslogik und verbindliche Regeln fuer die Ground Truth festlegen | X80: Fachliche Zieldefinition; Bewertungsleitfaden; priorisierte Entscheidungsregeln; abgenommene Akzeptanz- und Abgrenzungskriterien | Y80: Leitfaden und Regeln durch Fachlead freigegeben
P81: P1 | Q81: Ground Truth & Kalibrierung | R81: Key User / SMEs Landi | S81: Landi | T81: 10 | U81: W1, W2 | V81: Ground Truth erheben, labeln, konsolidieren und Abnahmekriterien fixieren | W81: Referenzfaelle fachlich labeln, kommentieren und strittige Faelle aufloesen | X81: Annotiertes Fallset; Referenzentscheidungen inkl. Begruendung; Edge-Case-Liste; dokumentierte Abweichungen fuer Adjudication | Y81: Gold-Set und Shadow-Set vollstaendig gelabelt
P82: P1 | Q82: Ground Truth & Kalibrierung | R82: Projektleitung / Delivery Lead | S82: Zuehlke | T82: 2 | U82: W1, W2 | V82: Ground Truth erheben, labeln, konsolidieren und Abnahmekriterien fixieren | W82: PoC-Setup, Arbeitsmodus, Review-Kadenz und Entscheidungsprozess mit Landi aufsetzen | X82: Kickoff-Unterlagen; abgestimmter Termin- und Review-Plan; Entscheidungs- und Eskalationslog; finaler Validierungsplan fuer Phase 1 | Y82: Kickoff erfolgt; Review-Kadenz bestaetigt; Ground-Truth-Vorgehen freigegeben
P83: P1 | Q83: Ground Truth & Kalibrierung | R83: Business Analyst / Quality Assurance | S83: Zuehlke | T83: 2 | U83: W1, W2 | V83: Ground Truth erheben, labeln, konsolidieren und Abnahmekriterien fixieren | W83: Test- und Bewertungsmethodik fuer die spaetere PoC-Validierung aufsetzen | X83: Test- und Bewertungsmatrix; Definition Gold-Set vs. Shadow-Set; Defect-Klassifikation fuer spaetere Abweichungen | Y83: Bewertungsmatrix freigegeben
P84: P1 | Q84: Ground Truth & Kalibrierung | R84: Solution Architect / Lead Engineer | S84: Zuehlke | T84: 1 | U84: W1, W2 | V84: Ground Truth erheben, labeln, konsolidieren und Abnahmekriterien fixieren | W84: Ground-Truth-relevante System- und Datenperspektive fuer die spaetere Agentenbewertung einbringen | X84: Entscheidungsobjekt-Entwurf; Liste technischer Muss-Attribute; Bewertungsrelevante Architekturannahmen | Y84: Technische Muss-Attribute fuer die Validierung definiert
P85: P2 | Q85: Detaildesign & Datenvorbereitung | R85: AI Engineer / Data Scientist | S85: Zuehlke | T85: 3 | U85: W3 | V85: Daten, Regeln und Agenten-Design auf PoC-Niveau spezifizieren | W85: Agentenrollen, I/O-Vertraege, Prompt-Strategie und Entscheidungslogik spezifizieren | X85: Agentenrollenbeschreibung; Input-/Output-Schemata; Prompt-/Instruktionsstrategie; Entscheidungs- und Eskalationsschema | Y85: Agenten-Spezifikation abgestimmt
P86: P2 | Q86: Detaildesign & Datenvorbereitung | R86: AI Engineer / Data Scientist | S86: Zuehlke | T86: 0.5 | U86: W3 | V86: Daten, Regeln und Agenten-Design auf PoC-Niveau spezifizieren | W86: Runtime-Komponenten, API-/Service-Schnitt und technische Review-Oberflaeche spezifizieren | X86: Technisches Runtime-Design; API-/Service-Schnittstellen; Logging-/Tracing-Design; UI-/Review-Komponenten-Skizze | Y86: Technische Komponentenliste freigegeben
P87: P2 | Q87: Detaildesign & Datenvorbereitung | R87: Business Analyst / Quality Assurance | S87: Zuehlke | T87: 1 | U87: W3 | V87: Daten, Regeln und Agenten-Design auf PoC-Niveau spezifizieren | W87: User Journey, Review-Flow und Bedienkonzept fuer Fachanwender konkretisieren | X87: User Journey fuer Startszenario; Review-/Freigabeflow; Wireframe-Skizzen; Rollen-/Aktionsmatrix | Y87: Review-Flow freigegeben
... P131: P7 | Q131: Dokumentation | R131: Fachlead / Product Owner Landi | S131: Landi | T131: 2 | U131: W9 | V131: Zusätzlich Informationen aufbereiten und bereitstellen | W131: Zusätzlich Informationen aufbereiten und bereitstellen | X131: Abschlussdokumentation | Y131: Abschlussdokumentation

Sheet 05_KOSTEN_MODELL
B2: Kostenmodell: Usage, Implementierung, OPEX und 5Y TCO
B4: 1) Usage- und Kapazitätsbaseline
B5: Treiber | C5: Y1 | D5: Y2 | E5: Y3 | F5: Y4 | G5: Y5 | H5: Kommentar
B6: Potenzielle Nutzer | C6: ='02_INPUTS'!D10 -> 654 | D6: ='02_INPUTS'!D10 -> 654 | E6: ='02_INPUTS'!D10 -> 654 | F6: ='02_INPUTS'!D10 -> 654 | G6: ='02_INPUTS'!D10 -> 654 | H6: Gesamtnutzer aus Input-Sheet
B7: Aktive Nutzerquote | C7: ='02_INPUTS'!D18 -> 0.35 | D7: ='02_INPUTS'!E18 -> 0.6 | E7: ='02_INPUTS'!F18 -> 0.75 | F7: ='02_INPUTS'!G18 -> 0.9 | G7: ='02_INPUTS'!H18 -> 0.9 | H7: Ramp-up der Adoption
B8: Monatlich aktive Nutzer | C8: =C6*C7 -> 228.9 | D8: =D6*D7 -> 392.4 | E8: =E6*E7 -> 490.5 | F8: =F6*F7 -> 588.6 | G8: =G7*G6 -> 588.6 | H8: Monatlich aktive Nutzer
B9: Jährliche Interaktionen | C9: =C$8*'02_INPUTS'!$D$19*'02_INPUTS'!$D$11*'02_INPUTS'!$D$26 -> 1142668.8 | D9: =D$8*'02_INPUTS'!$D$19*'02_INPUTS'!$D$11*'02_INPUTS'!$D$26 -> 1958860.8 | E9: =E$8*'02_INPUTS'!$D$19*'02_INPUTS'!$D$11*'02_INPUTS'!$D$26 -> 2448576 | F9: =F$8*'02_INPUTS'!$D$19*'02_INPUTS'!$D$11*'02_INPUTS'!$D$26 -> 2938291.2 | G9: =G$8*'02_INPUTS'!$D$19*'02_INPUTS'!$D$11*'02_INPUTS'!$D$26 -> 2938291.2 | H9: Treiber für variable Kosten und Nutzenramp-up
B10: Jährliche Input-Tokens | C10: =C9*('02_INPUTS'!D20+'02_INPUTS'!D22*'02_INPUTS'!D23) -> 2.9480855e+09 | D10: =D9*('02_INPUTS'!D20+'02_INPUTS'!D22*'02_INPUTS'!D23) -> 5.0538609e+09 | E10: =E9*('02_INPUTS'!D20+'02_INPUTS'!D22*'02_INPUTS'!D23) -> 6317326080 | F10: =F9*('02_INPUTS'!D20+'02_INPUTS'!D22*'02_INPUTS'!D23) -> 7.5807913e+09 | G10: =G9*('02_INPUTS'!D20+'02_INPUTS'!D22*'02_INPUTS'!D23) -> 7.5807913e+09 | H10: Text + bildbezogene Zusatztokens
B11: Jährliche Output-Tokens | C11: =C9*'02_INPUTS'!D21 -> 5.713344e+08 | D11: =D9*'02_INPUTS'!D21 -> 9.794304e+08 | E11: =E9*'02_INPUTS'!D21 -> 1224288000 | F11: =F9*'02_INPUTS'!D21 -> 1469145600 | G11: =G9*'02_INPUTS'!D21 -> 1469145600 | H11: LLM Output
B12: Jährliche Retrieval-/RAG-Requests | C12: =C9*'02_INPUTS'!D24 -> 685601.28 | D12: =D9*'02_INPUTS'!D24 -> 1175316.5 | E12: =E9*'02_INPUTS'!D24 -> 1469145.6 | F12: =F9*'02_INPUTS'!D24 -> 1762974.7 | G12: =G9*'02_INPUTS'!D24 -> 1762974.7 | H12: Requests an Retrieval / Search / Vector
B13: Jährliche Interaktionen mit Aktion | C13: =C9*'02_INPUTS'!D25 -> 285667.2 | D13: =D9*'02_INPUTS'!D25 -> 489715.2 | E13: =E9*'02_INPUTS'!D25 -> 612144 | F13: =F9*'02_INPUTS'!D25 -> 734572.8 | G13: =G9*'02_INPUTS'!D25 -> 734572.8 | H13: Interaktionen, die einen Write-back / Tool Call auslösen
B14: Jährliche Flow-/Ablaufaktionen | C14: =C13*'02_INPUTS'!D26 -> 1142668.8 | D14: =D13*'02_INPUTS'!D26 -> 1958860.8 | E14: =E13*'02_INPUTS'!D26 -> 2448576 | F14: =F13*'02_INPUTS'!D26 -> 2938291.2 | G14: =G13*'02_INPUTS'!D26 -> 2938291.2 | H14: Für Flow-/Action-basierte Plattformlogik
B15: Peak Interaktionen pro Stunde | C15: =C9/('02_INPUTS'!D12*12*'02_INPUTS'!D13)*'02_INPUTS'!D27 -> 997.568 | D15: =D9/('02_INPUTS'!D12*12*'02_INPUTS'!D13)*'02_INPUTS'!D27 -> 1710.1166 | E15: =E9/('02_INPUTS'!D12*12*'02_INPUTS'!D13)*'02_INPUTS'!D27 -> 2137.6457 | F15: =F9/('02_INPUTS'!D12*12*'02_INPUTS'!D13)*'02_INPUTS'!D27 -> 2565.1749 | G15: =G9/('02_INPUTS'!D12*12*'02_INPUTS'!D13)*'02_INPUTS'!D27 -> 2565.1749 | H15: Hilft bei Kapazitäts- und GPU-Abschätzung
B16: Peak Tokens pro Sekunde | C16: =C15*(('02_INPUTS'!D20+'02_INPUTS'!D22*'02_INPUTS'!D23)+'02_INPUTS'!D21)/3600 -> 853.47484 | D16: =D15*(('02_INPUTS'!D20+'02_INPUTS'!D22*'02_INPUTS'!D23)+'02_INPUTS'!D21)/3600 -> 1463.0997 | E16: =E15*(('02_INPUTS'!D20+'02_INPUTS'!D22*'02_INPUTS'!D23)+'02_INPUTS'!D21)/3600 -> 1828.8747 | F16: =F15*(('02_INPUTS'!D20+'02_INPUTS'!D22*'02_INPUTS'!D23)+'02_INPUTS'!D21)/3600 -> 2194.6496 | G16: =G15*(('02_INPUTS'!D20+'02_INPUTS'!D22*'02_INPUTS'!D23)+'02_INPUTS'!D21)/3600 -> 2194.6496 | H16: Relevant für OSS-GPU-Sizing
B18: 2) Implementierungsinvestition
B19: Kostenbaustein | C19: Copilot Studio | D19: Azure Komponenten | E19: Open Source auf Azure | F19: GCP Vertex AI | G19: GCP Komponenten | H19: Kommentar
B20: PoC Kosten
B21: P0 Projektsteup PoC und PMO | C21: =VLOOKUP($B21,'04_PoC_MVP_Phasen'!$B$7:$L$22,11,FALSE)*'04_PoC_MVP_Phasen'!$D$64 -> 8500 | D21: =VLOOKUP($B21,'04_PoC_MVP_Phasen'!$B$7:$L$22,11,FALSE)*'04_PoC_MVP_Phasen'!$D$66 -> 11500 | E21: =VLOOKUP($B21,'04_PoC_MVP_Phasen'!$B$7:$L$22,11,FALSE)*'04_PoC_MVP_Phasen'!$D$67 -> 12000 | F21: =VLOOKUP($B21,'04_PoC_MVP_Phasen'!$B$7:$L$22,11,FALSE)*'04_PoC_MVP_Phasen'!$D$65 -> 10000 | G21: =VLOOKUP($B21,'04_PoC_MVP_Phasen'!$B$7:$L$22,11,FALSE)*'04_PoC_MVP_Phasen'!$D$68 -> 11000 | H21: Basis-PD
B22: P1 Ground Truth & Kalibrierung | C22: =VLOOKUP($B22,'04_PoC_MVP_Phasen'!$B$7:$L$22,11,FALSE)*'04_PoC_MVP_Phasen'!$D$64 -> 15300 | D22: =VLOOKUP($B22,'04_PoC_MVP_Phasen'!$B$7:$L$22,11,FALSE)*'04_PoC_MVP_Phasen'!$D$66 -> 20700 | E22: =VLOOKUP($B22,'04_PoC_MVP_Phasen'!$B$7:$L$22,11,FALSE)*'04_PoC_MVP_Phasen'!$D$67 -> 21600 | F22: =VLOOKUP($B22,'04_PoC_MVP_Phasen'!$B$7:$L$22,11,FALSE)*'04_PoC_MVP_Phasen'!$D$65 -> 18000 | G22: =VLOOKUP($B22,'04_PoC_MVP_Phasen'!$B$7:$L$22,11,FALSE)*'04_PoC_MVP_Phasen'!$D$68 -> 19800 | H22: Use cases und Sprach-Multiplikator
B23: P2 Detaildesign & Datenvorbereitung | C23: =VLOOKUP($B23,'04_PoC_MVP_Phasen'!$B$7:$L$22,11,FALSE)*'04_PoC_MVP_Phasen'!$D$64 -> 20400 | D23: =VLOOKUP($B23,'04_PoC_MVP_Phasen'!$B$7:$L$22,11,FALSE)*'04_PoC_MVP_Phasen'!$D$66 -> 27600 | E23: =VLOOKUP($B23,'04_PoC_MVP_Phasen'!$B$7:$L$22,11,FALSE)*'04_PoC_MVP_Phasen'!$D$67 -> 28800 | F23: =VLOOKUP($B23,'04_PoC_MVP_Phasen'!$B$7:$L$22,11,FALSE)*'04_PoC_MVP_Phasen'!$D$65 -> 24000 | G23: =VLOOKUP($B23,'04_PoC_MVP_Phasen'!$B$7:$L$22,11,FALSE)*'04_PoC_MVP_Phasen'!$D$68 -> 26400 | H23: Systeme x Security-Multiplikator x Hybrid-/On-Prem-Faktor
B24: P3 Runtime & Basisplattform | C24: =VLOOKUP($B24,'04_PoC_MVP_Phasen'!$B$7:$L$22,11,FALSE)*'04_PoC_MVP_Phasen'!$D$64 -> 20400 | D24: =VLOOKUP($B24,'04_PoC_MVP_Phasen'!$B$7:$L$22,11,FALSE)*'04_PoC_MVP_Phasen'!$D$66 -> 27600 | E24: =VLOOKUP($B24,'04_PoC_MVP_Phasen'!$B$7:$L$22,11,FALSE)*'04_PoC_MVP_Phasen'!$D$67 -> 28800 | F24: =VLOOKUP($B24,'04_PoC_MVP_Phasen'!$B$7:$L$22,11,FALSE)*'04_PoC_MVP_Phasen'!$D$65 -> 24000 | G24: =VLOOKUP($B24,'04_PoC_MVP_Phasen'!$B$7:$L$22,11,FALSE)*'04_PoC_MVP_Phasen'!$D$68 -> 26400 | H24: Wissensquellen
B25: P4 Agenten-Implementierung | C25: =VLOOKUP($B25,'04_PoC_MVP_Phasen'!$B$7:$L$22,11,FALSE)*'04_PoC_MVP_Phasen'!$D$64 -> 67150 | D25: =VLOOKUP($B25,'04_PoC_MVP_Phasen'!$B$7:$L$22,11,FALSE)*'04_PoC_MVP_Phasen'!$D$66 -> 90850 | E25: =VLOOKUP($B25,'04_PoC_MVP_Phasen'!$B$7:$L$22,11,FALSE)*'04_PoC_MVP_Phasen'!$D$67 -> 94800 | F25: =VLOOKUP($B25,'04_PoC_MVP_Phasen'!$B$7:$L$22,11,FALSE)*'04_PoC_MVP_Phasen'!$D$65 -> 79000 | G25: =VLOOKUP($B25,'04_PoC_MVP_Phasen'!$B$7:$L$22,11,FALSE)*'04_PoC_MVP_Phasen'!$D$68 -> 86900 | H25: Basis x Security-Multiplikator
B26: P5 Validierung & Tuning | C26: =VLOOKUP($B26,'04_PoC_MVP_Phasen'!$B$7:$L$22,11,FALSE)*'04_PoC_MVP_Phasen'!$D$64 -> 37400 | D26: =VLOOKUP($B26,'04_PoC_MVP_Phasen'!$B$7:$L$22,11,FALSE)*'04_PoC_MVP_Phasen'!$D$66 -> 50600 | E26: =VLOOKUP($B26,'04_PoC_MVP_Phasen'!$B$7:$L$22,11,FALSE)*'04_PoC_MVP_Phasen'!$D$67 -> 52800 | F26: =VLOOKUP($B26,'04_PoC_MVP_Phasen'!$B$7:$L$22,11,FALSE)*'04_PoC_MVP_Phasen'!$D$65 -> 44000 | G26: =VLOOKUP($B26,'04_PoC_MVP_Phasen'!$B$7:$L$22,11,FALSE)*'04_PoC_MVP_Phasen'!$D$68 -> 48400 | H26: Nutzerbasis / 100
B27: P6 Abschluss & MVP-Entscheid | C27: =VLOOKUP($B27,'04_PoC_MVP_Phasen'!$B$7:$L$22,11,FALSE)*'04_PoC_MVP_Phasen'!$D$64 -> 8500 | D27: =VLOOKUP($B27,'04_PoC_MVP_Phasen'!$B$7:$L$22,11,FALSE)*'04_PoC_MVP_Phasen'!$D$66 -> 11500 | E27: =VLOOKUP($B27,'04_PoC_MVP_Phasen'!$B$7:$L$22,11,FALSE)*'04_PoC_MVP_Phasen'!$D$67 -> 12000 | F27: =VLOOKUP($B27,'04_PoC_MVP_Phasen'!$B$7:$L$22,11,FALSE)*'04_PoC_MVP_Phasen'!$D$65 -> 10000 | G27: =VLOOKUP($B27,'04_PoC_MVP_Phasen'!$B$7:$L$22,11,FALSE)*'04_PoC_MVP_Phasen'!$D$68 -> 11000 | H27: Puffer auf PD-Zwischensumme
B28: P7 PoC-Dokumentation & Go/No-Go Vorlage | C28: =VLOOKUP($B28,'04_PoC_MVP_Phasen'!$B$7:$L$22,11,FALSE)*'04_PoC_MVP_Phasen'!$D$64 -> 5100 | D28: =VLOOKUP($B28,'04_PoC_MVP_Phasen'!$B$7:$L$22,11,FALSE)*'04_PoC_MVP_Phasen'!$D$66 -> 6900 | E28: =VLOOKUP($B28,'04_PoC_MVP_Phasen'!$B$7:$L$22,11,FALSE)*'04_PoC_MVP_Phasen'!$D$67 -> 7200 | F28: =VLOOKUP($B28,'04_PoC_MVP_Phasen'!$B$7:$L$22,11,FALSE)*'04_PoC_MVP_Phasen'!$D$65 -> 6000 | G28: =VLOOKUP($B28,'04_PoC_MVP_Phasen'!$B$7:$L$22,11,FALSE)*'04_PoC_MVP_Phasen'!$D$68 -> 6600 | H28: Einmalige Lizenzen / Tooling / Environments
B30: Externe Personentage gesamt | C30: =SUM('04_PoC_MVP_Phasen'!D22,'04_PoC_MVP_Phasen'!G22:J22)*'04_PoC_MVP_Phasen'!$D$64 -> 91.375 | D30: =SUM('04_PoC_MVP_Phasen'!D22,'04_PoC_MVP_Phasen'!G22:J22)*'04_PoC_MVP_Phasen'!$D$66 -> 123.625 | E30: =SUM('04_PoC_MVP_Phasen'!D22,'04_PoC_MVP_Phasen'!G22:J22)*'04_PoC_MVP_Phasen'!$D$67 -> 129 | F30: =SUM('04_PoC_MVP_Phasen'!D22,'04_PoC_MVP_Phasen'!G22:J22)*'04_PoC_MVP_Phasen'!$D$65 -> 107.5 | G30: =SUM('04_PoC_MVP_Phasen'!D22,'04_PoC_MVP_Phasen'!G22:J22)*'04_PoC_MVP_Phasen'!$D$68 -> 118.25 | H30: Relevant für externe Delivery-Steuerung
B31: Interne Personentage gesamt | C31: =SUM('04_PoC_MVP_Phasen'!E22,'04_PoC_MVP_Phasen'!F22)*'04_PoC_MVP_Phasen'!$D$64 -> 34.85 | D31: =SUM('04_PoC_MVP_Phasen'!E22,'04_PoC_MVP_Phasen'!F22)*'04_PoC_MVP_Phasen'!$D$66 -> 47.15 | E31: =SUM('04_PoC_MVP_Phasen'!E22,'04_PoC_MVP_Phasen'!F22)*'04_PoC_MVP_Phasen'!$D$67 -> 49.2 | F31: =SUM('04_PoC_MVP_Phasen'!E22,'04_PoC_MVP_Phasen'!F22)*'04_PoC_MVP_Phasen'!$D$65 -> 41 | G31: =SUM('04_PoC_MVP_Phasen'!E22,'04_PoC_MVP_Phasen'!F22)*'04_PoC_MVP_Phasen'!$D$68 -> 45.1 | H31: Relevante Business-/IT-Last intern
B32: Total Implementierungsinvestition | C32: =SUM(C21:C28) -> 182750 | D32: =SUM(D21:D28) -> 247250 | E32: =SUM(E21:E28) -> 258000 | F32: =SUM(F21:F28) -> 215000 | G32: =SUM(G21:G28) -> 236500 | H32: Einmalige Investition Y0
B33: Geschätzte PoC-Dauer | C33: =IFERROR(MAX(2,ROUNDUP(C30/(2*25),0)),0) -> 2 | D33: =IFERROR(MAX(2,ROUNDUP(D30/(2*25),0)),0) -> 3 | E33: =IFERROR(MAX(2,ROUNDUP(E30/(2*25),0)),0) -> 3 | F33: =IFERROR(MAX(2,ROUNDUP(F30/(2*25),0)),0) -> 3 | G33: =IFERROR(MAX(2,ROUNDUP(G30/(2*25),0)),0) -> 3 | H33: Grobe Schätzung auf Basis externer PD und paralleler Workstreams
B35: MVP Kosten
B36: ── Projektstart und Organisation ────── | C36: ='04_PoC_MVP_Phasen'!$L$30*'04_PoC_MVP_Phasen'!$D$64 -> 162180 | D36: ='04_PoC_MVP_Phasen'!$L$30*'04_PoC_MVP_Phasen'!$D$66 -> 219420 | E36: ='04_PoC_MVP_Phasen'!$L$30*'04_PoC_MVP_Phasen'!$D$67 -> 228960 | F36: ='04_PoC_MVP_Phasen'!$L$30*'04_PoC_MVP_Phasen'!$D$65 -> 190800 | G36: ='04_PoC_MVP_Phasen'!$L$30*'04_PoC_MVP_Phasen'!$D$68 -> 209880
B37: ── INTEGRATIONEN ─────────────── | C37: ='04_PoC_MVP_Phasen'!$L$35*'04_PoC_MVP_Phasen'!$D$64 -> 100300 | D37: ='04_PoC_MVP_Phasen'!$L$35*'04_PoC_MVP_Phasen'!$D$66 -> 135700 | E37: ='04_PoC_MVP_Phasen'!$L$35*'04_PoC_MVP_Phasen'!$D$67 -> 141600 | F37: ='04_PoC_MVP_Phasen'!$L$35*'04_PoC_MVP_Phasen'!$D$65 -> 118000 | G37: ='04_PoC_MVP_Phasen'!$L$35*'04_PoC_MVP_Phasen'!$D$68 -> 129800
B38: ── USE CASES ─────────────────── | C38: ='04_PoC_MVP_Phasen'!$L$42*'04_PoC_MVP_Phasen'!$D$64 -> 205700 | D38: ='04_PoC_MVP_Phasen'!$L$42*'04_PoC_MVP_Phasen'!$D$66 -> 278300 | E38: ='04_PoC_MVP_Phasen'!$L$42*'04_PoC_MVP_Phasen'!$D$67 -> 290400 | F38: ='04_PoC_MVP_Phasen'!$L$42*'04_PoC_MVP_Phasen'!$D$65 -> 242000 | G38: ='04_PoC_MVP_Phasen'!$L$42*'04_PoC_MVP_Phasen'!$D$68 -> 266200
B39: ── ABSCHLUSS ─────────────────── | C39: ='04_PoC_MVP_Phasen'!$L$51*'04_PoC_MVP_Phasen'!$D$64 -> 198900 | D39: ='04_PoC_MVP_Phasen'!$L$51*'04_PoC_MVP_Phasen'!$D$66 -> 269100 | E39: ='04_PoC_MVP_Phasen'!$L$51*'04_PoC_MVP_Phasen'!$D$67 -> 280800 | F39: ='04_PoC_MVP_Phasen'!$L$51*'04_PoC_MVP_Phasen'!$D$65 -> 234000 | G39: ='04_PoC_MVP_Phasen'!$L$51*'04_PoC_MVP_Phasen'!$D$68 -> 257400
B40: Externe Personentage gesamt | C40: =SUM('04_PoC_MVP_Phasen'!D58,'04_PoC_MVP_Phasen'!G58:J58)*'04_PoC_MVP_Phasen'!D64 -> 303.79 | D40: =SUM('04_PoC_MVP_Phasen'!D58,'04_PoC_MVP_Phasen'!G58:J58)*'04_PoC_MVP_Phasen'!D66 -> 411.01 | E40: =SUM('04_PoC_MVP_Phasen'!D58,'04_PoC_MVP_Phasen'!G58:J58)*'04_PoC_MVP_Phasen'!D67 -> 428.88 | F40: =SUM('04_PoC_MVP_Phasen'!D58,'04_PoC_MVP_Phasen'!G58:J58)*'04_PoC_MVP_Phasen'!D65 -> 357.4 | G40: =SUM('04_PoC_MVP_Phasen'!D58,'04_PoC_MVP_Phasen'!G58:J58)*'04_PoC_MVP_Phasen'!D68 -> 393.14
B41: Interne Personentage gesamt | C41: =SUM('04_PoC_MVP_Phasen'!E58:F58)*'04_PoC_MVP_Phasen'!D64 -> 110.5 | D41: =SUM('04_PoC_MVP_Phasen'!E58:F58)*'04_PoC_MVP_Phasen'!D66 -> 149.5 | E41: =SUM('04_PoC_MVP_Phasen'!E58:F58)*'04_PoC_MVP_Phasen'!D67 -> 156 | F41: =SUM('04_PoC_MVP_Phasen'!E58:F58)*'04_PoC_MVP_Phasen'!D65 -> 130 | G41: =SUM('04_PoC_MVP_Phasen'!E58:F58)*'04_PoC_MVP_Phasen'!D68 -> 143
B42: Total Implementierungsinvestition | C42: =SUM(C36:C39) -> 667080 | D42: =SUM(D36:D39) -> 902520 | E42: =SUM(E36:E39) -> 941760 | F42: =SUM(F36:F39) -> 784800 | G42: =SUM(G36:G39) -> 863280
B43: Geschätzte MVP-Dauer | C43: =IFERROR(MAX(2,ROUNDUP(C40/(1.5*25),0)),0) -> 9 | D43: =IFERROR(MAX(2,ROUNDUP(D40/(1.5*25),0)),0) -> 11 | E43: =IFERROR(MAX(2,ROUNDUP(E40/(1.5*25),0)),0) -> 12 | F43: =IFERROR(MAX(2,ROUNDUP(F40/(1.5*25),0)),0) -> 10 | G43: =IFERROR(MAX(2,ROUNDUP(G40/(1.5*25),0)),0) -> 11
B45: 3) Steady-State OPEX (Y4) – annualisierte Sicht
B46: Kostenbaustein | C46: Copilot Studio | D46: Azure Komponenten | E46: Open Source auf Azure | F46: GCP Vertex AI | G46: GCP Komponenten | H46: Kommentar
B47: Variable Nutzung / Token- & Creditsverbrauch | C47: ='03_SZENARIOS'!C20*'03_SZENARIOS'!C21*F9 -> 258569.63 | D47: =(('03_SZENARIOS'!D$18/1000000)*$F$10)+(('03_SZENARIOS'!D$19/1000000)*$F$11) -> 40989.162 | E47: =(('03_SZENARIOS'!E$18/1000000)*$F$10)+(('03_SZENARIOS'!E$19/1000000)*$F$11) -> 8197.8324 | F47: =(('03_SZENARIOS'!F$18/1000000)*$F$10)+(('03_SZENARIOS'!F$19/1000000)*$F$11) -> 16395.665 | G47: =(('03_SZENARIOS'!G$18/1000000)*$F$10)+(('03_SZENARIOS'!G$19/1000000)*$F$11) -> 32791.33 | H47: Copilot = Credits; Azure = Token/Embedding; Open Source = GPU-Inferenzcluster
B48: Fixe Nutzung Search / Gateway / Basisplattform | C48: ='03_SZENARIOS'!C22*12 -> 9900 | D48: ='03_SZENARIOS'!D22*12 -> 49645.2 | E48: ='03_SZENARIOS'!E22*12 -> 14071.2 | F48: ='03_SZENARIOS'!F22*12 -> 38478 | G48: ='03_SZENARIOS'!G22*12 -> 40854 | H48: Fixe Plattformbausteine; bei OSS inkl. CPU/App, Search/State und Storage
B49: Product Owner / Backlog (FTE) | C49: ='03_SZENARIOS'!C9*'02_INPUTS'!D42*12 -> 50400 | D49: ='03_SZENARIOS'!D9*'02_INPUTS'!D42*12 -> 58800 | E49: ='03_SZENARIOS'!E9*'02_INPUTS'!D42*12 -> 67200 | F49: ='03_SZENARIOS'!F9*'02_INPUTS'!D42*12 -> 50400 | G49: ='03_SZENARIOS'!G9*'02_INPUTS'!D42*12 -> 58800 | H49: Business Ownership
B50: Wissensmanagement / Content Ops (FTE) | C50: ='03_SZENARIOS'!C10*'02_INPUTS'!D44*12 -> 54600 | D50: ='03_SZENARIOS'!D10*'02_INPUTS'!D44*12 -> 54600 | E50: ='03_SZENARIOS'!E10*'02_INPUTS'!D44*12 -> 62400 | F50: ='03_SZENARIOS'!F10*'02_INPUTS'!D44*12 -> 54600 | G50: ='03_SZENARIOS'!G10*'02_INPUTS'!D44*12 -> 54600 | H50: Wissenspflege / Content Ops
B51: Plattform / Integration (FTE) | C51: ='03_SZENARIOS'!C11*'02_INPUTS'!D43*12 -> 86400 | D51: ='03_SZENARIOS'!D11*'02_INPUTS'!D43*12 -> 108000 | E51: ='03_SZENARIOS'!E11*'02_INPUTS'!D43*12 -> 129600 | F51: ='03_SZENARIOS'!F11*'02_INPUTS'!D43*12 -> 86400 | G51: ='03_SZENARIOS'!G11*'02_INPUTS'!D43*12 -> 108000 | H51: Engineering / Integration / DevOps
B52: QA / Analytics / Governance (FTE) | C52: ='03_SZENARIOS'!C12*'02_INPUTS'!D42*12 -> 33600 | D52: ='03_SZENARIOS'!D12*'02_INPUTS'!D42*12 -> 42000 | E52: ='03_SZENARIOS'!E12*'02_INPUTS'!D42*12 -> 50400 | F52: ='03_SZENARIOS'!F12*'02_INPUTS'!D42*12 -> 33600 | G52: ='03_SZENARIOS'!G12*'02_INPUTS'!D42*12 -> 42000 | H52: Qualität / Evaluierung / Reporting
B53: Externer Support / Managed Service | C53: ='03_SZENARIOS'!C13*12 -> 24000 | D53: ='03_SZENARIOS'!D13*12 -> 30000 | E53: ='03_SZENARIOS'!E13*12 -> 18000 | F53: ='03_SZENARIOS'!F13*12 -> 18000 | G53: ='03_SZENARIOS'!G13*12 -> 18000 | H53: Externe Supportleistungen
B54: Hypercare-Aufschlag auf FTE im Jahr 1 | C54: ='03_SZENARIOS'!C14*'02_INPUTS'!D44*12 -> 31200 | D54: ='03_SZENARIOS'!D14*'02_INPUTS'!D44*12 -> 31200 | E54: ='03_SZENARIOS'!E14*'02_INPUTS'!D44*12 -> 39000 | F54: ='03_SZENARIOS'!F14*'02_INPUTS'!D44*12 -> 31200 | G54: ='03_SZENARIOS'!G14*'02_INPUTS'!D44*12 -> 31200 | H54: Sicherheits-/Preis-/Unschärfepuffer
B55: Total OPEX p.a. | C55: =SUM(C47:C54) -> 548669.63 | D55: =SUM(D47:D54) -> 415234.36 | E55: =SUM(E47:E54) -> 388869.03 | F55: =SUM(F47:F54) -> 329073.66 | G55: =SUM(G47:G54) -> 386245.33 | H55: Steady-state OPEX Y4
B57: 4) Jährliche OPEX nach Szenario (Y1–Y5) und 5Y OPEX
B58: Szenario | C58: Y1 | D58: Y2 | E58: Y3 | F58: Y4 | G58: Y5 | H58: 5Y OPEX | I58: Kommentar
B59: Copilot Studio | C59: =(C47*C7/F7)+SUM(C48:C54) -> 390654.85 | D59: =($C$47*D7/$F$7)+SUM($C$48:$C$54) -> 462479.75 | E59: =($C$47*E7/$F$7)+SUM($C$48:$C$54) -> 505574.69 | F59: =($C$47*F7/$F$7)+SUM($C$48:$C$54) -> 548669.63 | G59: =($C$47*G7/$F$7)+SUM($C$48:$C$54) -> 548669.63 | H59: =SUM(C59:G59) -> 2456048.5 | I59: Open Source: API-Token-Kosten (Foundation Model) + Plattform-OPEX + FTE
B60: Azure Komponenten | C60: =(D47*C7/F7)+SUM(D48:D54) -> 390185.43 | D60: =($D$47*D7/$F$7)+SUM($D$48:$D$54) -> 401571.31 | E60: =($D$47*E7/$F$7)+SUM($D$48:$D$54) -> 408402.84 | F60: =($D$47*F7/$F$7)+SUM($D$48:$D$54) -> 415234.36 | G60: =($D$47*G7/$F$7)+SUM($D$48:$D$54) -> 415234.36 | H60: =SUM(C60:G60) -> 2030628.3 | I60: Azure: modular component basket + FTE operating model
B61: Open Source auf Azure | C61: =(E47*C7/F7)+SUM(E48:E54) -> 383859.25 | D61: =($E$47*D7/$F$7)+SUM($E$48:$E$54) -> 386136.42 | E61: =($E$47*E7/$F$7)+SUM($E$48:$E$54) -> 387502.73 | F61: =($E$47*F7/$F$7)+SUM($E$48:$E$54) -> 388869.03 | G61: =($E$47*G7/$F$7)+SUM($E$48:$E$54) -> 388869.03 | H61: =SUM(C61:G61) -> 1935236.5 | I61: Open Source: GPU + CPU/App + Search/State + Storage + Support + FTE-Modell
B62: GCP Vertex AI | C62: =(F47*C7/F7)+SUM(F48:F54) -> 319054.09 | D62: =($F$47*D7/$F$7)+SUM($F$48:$F$54) -> 323608.44 | E62: =($F$47*E7/$F$7)+SUM($F$48:$F$54) -> 326341.05 | F62: =($F$47*F7/$F$7)+SUM($F$48:$F$54) -> 329073.66 | G62: =($F$47*G7/$F$7)+SUM($F$48:$F$54) -> 329073.66 | H62: =SUM(C62:G62) -> 1627150.9 | I62: GCP Vertex AI: Gemini 3.1 Pro/Flash; Vertex AI Search; Dialogflow CX; EU Data Zone
B63: GCP Komponenten | C63: =(G47*C7/F7)+SUM(G48:G54) -> 366206.18 | D63: =($G$47*D7/$F$7)+SUM($G$48:$G$54) -> 375314.89 | E63: =($G$47*E7/$F$7)+SUM($G$48:$G$54) -> 380780.11 | F63: =($G$47*F7/$F$7)+SUM($G$48:$G$54) -> 386245.33 | G63: =($G$47*G7/$F$7)+SUM($G$48:$G$54) -> 386245.33 | H63: =SUM(C63:G63) -> 1894791.8 | I63: GCP Custom: Cloud Run + ADK + Gemini direkt + Firestore Vector Search
B65: 5) 5Y TCO Übersicht
B66: Messgrösse | C66: Copilot Studio | D66: Azure Komponenten | E66: Open Source auf Azure | F66: GCP Vertex AI | G66: GCP Komponenten | H66: Kommentar
B67: Einmalige Implementierungsinvestition | C67: =C32+C42 -> 849830 | D67: =D32+D42 -> 1149770 | E67: =E32+E42 -> 1199760 | F67: =F32+F42 -> 999800 | G67: =G32+G42 -> 1099780 | H67: Aus Abschnitt 2
B68: 5Y OPEX | C68: =H59 -> 2456048.5 | D68: =H60 -> 2030628.3 | E68: =H61 -> 1935236.5 | F68: =H62 -> 1627150.9 | G68: =H63 -> 1894791.8 | H68: Aus Abschnitt 4
B69: 5Y TCO | C69: =C67+C68 -> 3305878.5 | D69: =D67+D68 -> 3180398.3 | E69: =E67+E68 -> 3134996.5 | F69: =F67+F68 -> 2626950.9 | G69: =G67+G68 -> 2994571.8 | H69: Invest + OPEX
B70: Steady-state OPEX p.a. (Y4) | C70: =C55 -> 548669.63 | D70: =D55 -> 415234.36 | E70: =E55 -> 388869.03 | F70: =F55 -> 329073.66 | G70: =G55 -> 386245.33 | H70: Jahr 4

Sheet 06_NUTZEN_MODELL
B2: Nutzenmodell: Landi Top-down, Workshop Bottom-up und kommerzielle Hebel
B4: 1) Landi Top-down-Nutzenmodell (operativ / Effizienz)
B5: Nutzenhebel | C5: Treiber / Fälle p.a. | D5: Modell CHF p.a. | E5: Landi Referenz CHF p.a. | F5: Ausgewählt CHF p.a. | G5: Stunden p.a. | H5: FTE / AE p.a. | I5: Kommentar
B6: Unnötige Service-Aufträge vermeiden | C6: =IF('02_INPUTS'!D54>0,'02_INPUTS'!D54,'02_INPUTS'!D50*'02_INPUTS'!D51) -> 13400 | D6: =C6*'02_INPUTS'!D52/60*'02_INPUTS'!D39 -> 282516.67 | E6: 281000 | F6: =IF(D6>0,D6,C6) -> 282516.67 | G6: =C6*'02_INPUTS'!D52/60 -> 5136.6667 | H6: =G6/'02_INPUTS'!D41 -> 2.8537037 | I6: Referenz: 13’400 SA / CHF 281k
B7: Admin-Aufwand retournierte SA reduzieren | C7: ='02_INPUTS'!D50 -> 50690 | D7: =C7*'02_INPUTS'!D53/60*'02_INPUTS'!D40 -> 101380 | E7: 97620 | F7: =IF(D7>0,D7,C7) -> 101380 | G7: =C7*'02_INPUTS'!D53/60 -> 1689.6667 | H7: =G7/'02_INPUTS'!D41 -> 0.9387037 | I7: Landi Referenz: 2 Min pro retournierter SA
B8: Direktgutschriften reduzieren | C8: =IF('02_INPUTS'!D62>0,'02_INPUTS'!D62,'02_INPUTS'!D59*'02_INPUTS'!D61) -> 20475 | D8: =IF('02_INPUTS'!D62>0,C8*('02_INPUTS'!D60/'02_INPUTS'!D59),'02_INPUTS'!D60*'02_INPUTS'!D61) -> 562867.65 | E8: ='02_INPUTS'!D63 -> 697289 | F8: =IF(D8>0,D8,C8) -> 562867.65 | G8: 0 | H8: =G8/'02_INPUTS'!D41 -> 0 | I8: Landi Referenz: CHF 697’289
B9: Schriftliche Anfragen vermeiden | C9: =IF('02_INPUTS'!D55>0,'02_INPUTS'!D55,0) -> 40620 | D9: =C9*'02_INPUTS'!D56/60*'02_INPUTS'!D40 -> 406200 | E9: 406200 | F9: =IF(D9>0,D9,C9) -> 406200 | G9: =C9*'02_INPUTS'!D56/60 -> 6770 | H9: =G9/'02_INPUTS'!D41 -> 3.7611111 | I9: Landi Referenz: 40’620 Anfragen
B10: Aufwand auf restlichen Anfragen reduzieren | C10: =IF('02_INPUTS'!D58>0,'02_INPUTS'!D58,MAX('02_INPUTS'!D48-C9,0)) -> 162480 | D10: =C10*'02_INPUTS'!D56*'02_INPUTS'!D57/60*'02_INPUTS'!D40 -> 541058.4 | E10: 541080 | F10: =IF(D10>0,D10,C10) -> 541058.4 | G10: =C10*'02_INPUTS'!D56*'02_INPUTS'!D57/60 -> 9017.64 | H10: =G10/'02_INPUTS'!D41 -> 5.0098 | I10: Landi Referenz: 162’480 Restanfragen
B11: Brutto-Effizienzpotenzial p.a. | F11: =SUM(F6:F10) -> 1894022.7 | I11: Brutto = Summe der fünf Landi-Top-down-Kategorien
B12: Konservativer Wirkungsgrad Effizienz | F12: ='02_INPUTS'!D64 -> 0.75 | I12: Default 75% gemäss Legacy-Annahme
B13: Konservatives Effizienzpotenzial p.a. | F13: =F11*F12 -> 1420517 | I13: Basiscase Effizienzpotenzial p.a.
B14: Stunden gesamt p.a. | F14: =SUM(G6:G10) -> 22613.973 | I14: Rechnerische Stundenfreisetzung
B15: FTE / AE gesamt | F15: =SUM(H6:H10) -> 12.563319 | H15: =SUM(H6:H10) -> 12.563319 | I15: Rechnerische FTE-Äquivalente
B18: 2) Workshop Bottom-up Crosscheck
B19: Task & Business Context | E19: Volumen / Zeit / Arbeitsnutzen (Nutzen durch schnellere Ausführung) | U19: Outcome-basierter Nutzen (Nutzen durch vermiedene unnötige Service-Arbeiten oder Zusatzumsatz)
B20: ID | C20: Task | D20: Primärer Business Case | E20: Cases CH | F20: Cases Laden | G20: Adoptionsrate (Landi CH) | H20: Adoptionsrate (Landi Laden) | I20: Erfolgsquote KI | J20: KI-genutzte Cases (Landi CH) p.a. | K20: Erfolgreiche Cases (Landi CH) p.a. | L20: Erfolgreiche Cases (Landi Laden) p.a. | M20: KI-genutzte Cases (Landi Laden) | N20: Zeitaufwand heute (min) | O20: Zeitaufwand mit AI (min) | P20: Eingesparte Zeit (min) | Q20: Kosten pro Minute Landi CH (CHF) | R20: Kosten pro Minute Landi Laden (CHF) | S20: Arbeitsnutzen p.a. Landi CH (CHF) | T20: Arbeitsnutzen p.a. Landi Laden (CHF) | U20: Vermiedene Serviceaufträge / Jahr | V20: Kosten pro Serviceauftrag (CHF) | W20: Nutzen vermiedene Serviceaufträge (CHF) | X20: Vermiedene Direktgutschriften / Jahr | Y20: Kosten pro Direktgutschrift (CHF) | Z20: Nutzen vermiedene Direktgutschriften (CHF) | AA20: Zusätzlicher Deckungsbeitrag p.a. (CHF) | AB20: Zusätzliche Ersatzteilverkäufe / Jahr | AC20: Nutzen pro Ersatzteilverkauf (CHF) | AD20: Nutzen zusätzliche Ersatzteilverkäufe (CHF) | AE20: Landi CH-Bruttonutzen p.a. (CHF) | AF20: Landi Laden-Bruttonutzen p.a. (CHF) | AG20: Gesamt-Bruttonutzen p.a. (CHF)
B21: 1 | C21: Produkt identifizieren | D21: Bearbeitungszeit reduzieren | E21: 10000 | F21: 500000 | G21: 0.95 | H21: 0.7 | I21: 0.85 | J21: =E21*G21 -> 9500 | K21: =J21*I21 -> 8075 | L21: =M21*I21 -> 297500 | M21: =F21*H21 -> 350000 | N21: 2 | O21: 0.5 | P21: =MAX(N21-O21,0) -> 1.5 | Q21: 1 | R21: 0.83 | S21: =K21*P21*Q21 -> 12112.5 | T21: =L21*P21*R21 -> 370387.5 | W21: =U21*V21 -> 0 | Z21: =X21*Y21 -> 0 | AA21: 0 | AE21: =SUM(S21,W21,Z21,AA21, AD21) -> 12112.5 | AF21: =SUM(T21) -> 370387.5 | AG21: =SUM(S21,T21,W21,Z21,AA21, AD21) -> 382500
B22: 2 | C22: Produktinformationen bereitstellen | D22: Bearbeitungszeit reduzieren | E22: 10000 | F22: 500000 | G22: 0.95 | H22: 0.7 | I22: 0.95 | J22: =E22*G22 -> 9500 | K22: =J22*I22 -> 9025 | L22: =M22*I22 -> 332500 | M22: =F22*H22 -> 350000 | N22: 3 | O22: 1 | P22: =MAX(N22-O22,0) -> 2 | Q22: 1 | R22: 0.83 | S22: =K22*P22*Q22 -> 18050 | T22: =L22*P22*R22 -> 551950 | U22: 0 | V22: 0 | W22: =U22*V22 -> 0 | X22: 0 | Y22: 0 | Z22: =X22*Y22 -> 0 | AA22: 0 | AE22: =SUM(S22,W22,Z22,AA22, AD22) -> 18050 | AF22: =SUM(T22) -> 551950 | AG22: =SUM(S22,T22,W22,Z22,AA22, AD22) -> 570000
B23: 3 | C23: Diagnose durchführen | D23: Reduktion der Anfragen | E23: 58000 | F23: 101000 | G23: 1 | H23: 1 | I23: 0.95 | J23: =E23*G23 -> 58000 | K23: =J23*I23 -> 55100 | L23: =M23*I23 -> 95950 | M23: =F23*H23 -> 101000 | N23: 5 | O23: 5 | P23: =MAX(N23-O23,0) -> 0 | Q23: 1 | R23: 0.83 | S23: =K23*P23*Q23 -> 0 | T23: =L23*P23*R23 -> 0 | U23: 6500 | V23: 47.9 | W23: =U23*V23 -> 311350 | X23: 10000 | Y23: 27.5 | Z23: =X23*Y23 -> 275000 | AA23: 0 | AE23: =SUM(S23,W23,Z23,AA23, AD23) -> 586350 | AF23: =SUM(T23) -> 0 | AG23: =SUM(S23,T23,W23,Z23,AA23, AD23) -> 586350
B24: 4 | C24: Handlungsoptionen empfehlen | D24: Serviceaufträge vermeiden | E24: 58000 | F24: 101000 | G24: 1 | H24: 1 | I24: 0.95 | J24: =E24*G24 -> 58000 | K24: =J24*I24 -> 55100 | L24: =M24*I24 -> 95950 | M24: =F24*H24 -> 101000 | N24: 5 | O24: 5 | P24: =MAX(N24-O24,0) -> 0 | Q24: 1 | R24: 0.83 | S24: =K24*P24*Q24 -> 0 | T24: =L24*P24*R24 -> 0 | U24: 6500 | V24: 47.9 | W24: =U24*V24 -> 311350 | X24: 10000 | Y24: 27.5 | Z24: =X24*Y24 -> 275000 | AA24: 0 | AE24: =SUM(S24,W24,Z24,AA24, AD24) -> 586350 | AF24: =SUM(T24) -> 0 | AG24: =SUM(S24,T24,W24,Z24,AA24, AD24) -> 586350
B25: 5 | C25: Ersatzteil identifizieren | D25: Ersatzteilumsatz erhöhen | E25: 5000 | F25: 50000 | G25: 0.95 | H25: 0.7 | I25: 0.95 | J25: =E25*G25 -> 4750 | K25: =J25*I25 -> 4512.5 | L25: =M25*I25 -> 33250 | M25: =F25*H25 -> 35000 | N25: 1 | O25: 0.5 | P25: =MAX(N25-O25,0) -> 0.5 | Q25: 1 | R25: 0.83 | S25: =K25*P25*Q25 -> 2256.25 | T25: =L25*P25*R25 -> 13798.75 | U25: 0 | V25: 0 | W25: =U25*V25 -> 0 | X25: 0 | Y25: 0 | Z25: =X25*Y25 -> 0 | AA25: 0 | AB25: =236874*0.1 -> 23687.4 | AC25: =6*0.25 -> 1.5 | AD25: =AB25*AC25 -> 35531.1 | AE25: =SUM(S25,W25,Z25,AA25, AD25) -> 37787.35 | AF25: =SUM(T25) -> 13798.75 | AG25: =SUM(S25,T25,W25,Z25,AA25, AD25) -> 51586.1
B26: 8 | C26: Garantie prüfen | D26: Direktgutschriften vermeiden | E26: 66000 | F26: 101000 | G26: 1 | H26: 1 | I26: 0.95 | J26: =E26*G26 -> 66000 | K26: =J26*I26 -> 62700 | L26: =M26*I26 -> 95950 | M26: =F26*H26 -> 101000 | N26: 2 | O26: 1.5 | P26: =MAX(N26-O26,0) -> 0.5 | Q26: 1 | R26: 0.83 | S26: =K26*P26*Q26 -> 31350 | T26: =L26*P26*R26 -> 39819.25 | U26: 0 | V26: 0 | W26: =U26*V26 -> 0 | X26: 0 | Y26: 0 | Z26: =X26*Y26 -> 0 | AA26: 0 | AE26: =SUM(S26,W26,Z26,AA26, AD26) -> 31350 | AF26: =SUM(T26) -> 39819.25 | AG26: =SUM(S26,T26,W26,Z26,AA26, AD26) -> 71169.25
B27: 9 | C27: Anfrage (Case) vorbereiten | D27: Bearbeitungszeit reduzieren | E27: 100000 | F27: 200000 | G27: 0.95 | H27: 0.7 | I27: 0.95 | J27: =E27*G27 -> 95000 | K27: =J27*I27 -> 90250 | L27: =M27*I27 -> 133000 | M27: =F27*H27 -> 140000 | N27: 2 | O27: 1 | P27: =MAX(N27-O27,0) -> 1 | Q27: 1 | R27: 0.83 | S27: =K27*P27*Q27 -> 90250 | T27: =L27*P27*R27 -> 110390 | U27: 0 | V27: 0 | W27: =U27*V27 -> 0 | X27: 0 | Y27: 0 | Z27: =X27*Y27 -> 0 | AA27: 0 | AE27: =SUM(S27,W27,Z27,AA27, AD27) -> 90250 | AF27: =SUM(T27) -> 110390 | AG27: =SUM(S27,T27,W27,Z27,AA27, AD27) -> 200640
B28: 10 | C28: Dokumentation optimieren | D28: Dokumentationsqualität steigern | E28: 47000 | F28: 0 | G28: 1 | I28: 0.95 | J28: =E28*G28 -> 47000 | K28: =J28*I28 -> 44650 | L28: =M28*I28 -> 0 | M28: =F28*H28 -> 0 | N28: 3.5 | O28: 2 | P28: =MAX(N28-O28,0) -> 1.5 | Q28: 1 | R28: 0.83 | S28: =K28*P28*Q28 -> 66975 | T28: =L28*P28*R28 -> 0 | U28: 0 | V28: 0 | W28: =U28*V28 -> 0 | X28: 0 | Y28: 0 | Z28: =X28*Y28 -> 0 | AA28: 0 | AE28: =SUM(S28,W28,Z28,AA28, AD28) -> 66975 | AF28: =SUM(T28) -> 0 | AG28: =SUM(S28,T28,W28,Z28,AA28, AD28) -> 66975
B29: TOTAL | E29: =SUM(E21:E28) -> 354000 | F29: =SUM(F21:F28) -> 1553000 | G29: =AVERAGE(G21:G28) -> 0.975 | H29: =AVERAGE(H21:H28) -> 0.82857143 | I29: =AVERAGE(I21:I28) -> 0.9375 | J29: =SUM(J21:J28) -> 347750 | K29: =SUM(K21:K28) -> 329412.5 | L29: =SUM(L21:L28) -> 1084100 | M29: =SUM(M21:M28) -> 1178000 | N29: =AVERAGE(N21:N28) -> 2.9375 | O29: =AVERAGE(O21:O28) -> 2.0625 | P29: =AVERAGE(P21:P28) -> 0.875 | Q29: =AVERAGE(Q21:Q28) -> 1 | R29: =AVERAGE(R21:R28) -> 0.83 | S29: =SUM(S21:S28) -> 220993.75 | T29: =SUM(T21:T28) -> 1086345.5 | U29: =SUM(U21:U28) -> 13000 | V29: =AVERAGE(V23:V24) -> 47.9 | W29: =SUM(W21:W28) -> 622700 | X29: =SUM(X21:X28) -> 20000 | Y29: =AVERAGE(Y23:Y24) -> 27.5 | Z29: =SUM(Z21:Z28) -> 550000 | AE29: =SUM(AE21:AE28) -> 1429224.9 | AF29: =SUM(AF21:AF28) -> 1086345.5 | AG29: =SUM(AG21:AG28) -> 2515570.4
B30: Interpretation: Der Bottom-up Workshop ergibt rund CHF 2.52 Mio. Bruttonutzen p.a. für die quantifizierten Tasks für die Landi CH und die Landi Läden. Die Landi CH liegt mit einem geschätzten Nutzen von 1.42 Mio. genau im selben Bereich wie die Top-down_Schätzung. Die Legacy-Annahme von CHF 1.52 Mio. p.a. (75% Wirkung) ist daher realistisch. | I30: Bottom-up liegt über Top-down und bestätigt, dass die Legacy-Annahme konservativ ist.
B32: 3) Kommerzielle Upside und ausgewählter Basiscase
B33: Hebel | C33: Treiber | D33: Brutto CHF p.a. | E33: Kommentar
B34: landi.ch Conversion-Uplift (aktuell → neu) | C34: =MAX('02_INPUTS'!D71*'02_INPUTS'!D75-'02_INPUTS'!D71*'02_INPUTS'!D73,0) -> 18004 | D34: =C34*'02_INPUTS'!D67*'02_INPUTS'!D77 -> 475100.35 | E34: Primäre eCommerce-Upside
B35: landi.ch Conversion-Uplift (Budget 2026 → neu) | C35: =MAX('02_INPUTS'!D72*'02_INPUTS'!D75-'02_INPUTS'!D72*'02_INPUTS'!D74,0) -> 14125 | D35: =C35*'02_INPUTS'!D69*'02_INPUTS'!D77 -> 379614.74 | E35: Alternative Sicht vs Budgetziel
B36: Stationärer Basket-Uplift | C36: ='02_INPUTS'!D76*'02_INPUTS'!D78*'02_INPUTS'!D79 -> 0 | D36: =C36*'02_INPUTS'!D77 -> 0 | E36: Nur aktivieren, wenn Attribution belastbar
B37: Stationäre Frequenz-Uplift | C37: ='02_INPUTS'!D76*'02_INPUTS'!D80 -> 0 | D37: =C37*'02_INPUTS'!D77 -> 0 | E37: Konservativ default = 0
B38: Ersatzteil-Umsatz-Uplift | C38: ='02_INPUTS'!D83*'02_INPUTS'!D85 -> 0 | D38: =C38*'02_INPUTS'!D84 -> 0 | E38: Aus Workshop-Spare-Parts-Revenue ableitbar
B39: Brutto kommerzielle Upside p.a. | D39: =SUM(D34,D36:D38) -> 475100.35 | E39: Budget-Alternative in D34 bewusst nicht im Basistotal
B40: Konservative kommerzielle Upside p.a. | D40: =D39*'02_INPUTS'!D82 -> 237550.18 | E40: Vor Szenario-Realisierung, aber nach Haircut
B41: Ausgewählter Basiscase p.a. | D41: =F13+D40*'02_INPUTS'!D81 -> 1420517 | E41: Effizienz + optionale kommerzielle Upside
B42: Optionales Potenzial p.a. inkl. kommerzieller Upside | D42: =F13+D40 -> 1658067.2 | E42: Nur zur Sensitivität
B43: Legacy konservativer Nutzen p.a. | D43: 1517392 | E43: Aus Altmodell / Landi Working Assumption
B44: Delta ausgewählter Basiscase vs Legacy | D44: =D41-D43 -> -96874.96 | E44: Soll nahe 0 bleiben bei deaktivierter Upside
B45: Workshop brutto p.a. | D45: =AE29 -> 1429224.9 | E45: Bottom-up Crosscheck
B46: Verhältnis Top-down brutto zu Workshop brutto | D46: =F11/D45 -> 1.3252098 | E46: Wert < 100% = Top-down konservativer

Sheet 07_VALUE_CASE
B2: Szenariobasierter Wertbeitrag, Payback und strategische Einordnung
B4: Messgrösse | C4: Copilot Studio | D4: Azure Komponenten | E4: Open Source auf Azure | F4: GCP Vertex AI | G4: GCP Komponenten | H4: Kommentar
B5: Realisierungsfaktor Effizienznutzen | C5: ='03_SZENARIOS'!C45 -> 0.85 | D5: ='03_SZENARIOS'!D45 -> 0.95 | E5: ='03_SZENARIOS'!E45 -> 0.95 | F5: ='03_SZENARIOS'!F45 -> 0.9 | G5: ='03_SZENARIOS'!G45 -> 0.95 | H5: Aus Szenario-Narrativ abgeleitet; editierbar
B6: Realisierungsfaktor kommerzielle Upside | C6: ='03_SZENARIOS'!C46 -> 0.45 | D6: ='03_SZENARIOS'!D46 -> 0.85 | E6: ='03_SZENARIOS'!E46 -> 0.9 | F6: ='03_SZENARIOS'!F46 -> 0.7 | G6: ='03_SZENARIOS'!G46 -> 0.85 | H6: Kommerzielle Hebel brauchen tiefere Integration
B7: Steady-state Effizienznutzen p.a. | C7: ='06_NUTZEN_MODELL'!F13*C5 -> 1207439.5 | D7: ='06_NUTZEN_MODELL'!F13*D5 -> 1349491.2 | E7: ='06_NUTZEN_MODELL'!F13*E5 -> 1349491.2 | F7: ='06_NUTZEN_MODELL'!F13*F5 -> 1278465.3 | G7: ='06_NUTZEN_MODELL'!F13*G5 -> 1349491.2 | H7: Nur konservativer Effizienznutzen
B8: Steady-state kommerzielle Upside p.a. | C8: ='06_NUTZEN_MODELL'!D40*C6*'02_INPUTS'!D81 -> 0 | D8: ='06_NUTZEN_MODELL'!D40*D6*'02_INPUTS'!D81 -> 0 | E8: ='06_NUTZEN_MODELL'!D40*E6*'02_INPUTS'!D81 -> 0 | F8: ='06_NUTZEN_MODELL'!D40*F6*'02_INPUTS'!D81 -> 0 | G8: ='06_NUTZEN_MODELL'!D40*G6*'02_INPUTS'!D81 -> 0 | H8: Kommerzielle Upside nur bei aktiviertem Schalter
B9: Steady-state Gesamtpotenzial p.a. | C9: =C7+C8 -> 1207439.5 | D9: =D7+D8 -> 1349491.2 | E9: =E7+E8 -> 1349491.2 | F9: =F7+F8 -> 1278465.3 | G9: =G7+G8 -> 1349491.2 | H9: Steady-state p.a.
B10: Ramp-up Faktor Y1 | C10: =IFERROR('05_KOSTEN_MODELL'!C9/'05_KOSTEN_MODELL'!F9,0) -> 0.38888889 | D10: =IFERROR('05_KOSTEN_MODELL'!C9/'05_KOSTEN_MODELL'!F9,0) -> 0.38888889 | E10: =IFERROR('05_KOSTEN_MODELL'!C9/'05_KOSTEN_MODELL'!F9,0) -> 0.38888889 | F10: =IFERROR('05_KOSTEN_MODELL'!C9/'05_KOSTEN_MODELL'!F9,0) -> 0.38888889 | G10: =IFERROR('05_KOSTEN_MODELL'!C9/'05_KOSTEN_MODELL'!F9,0) -> 0.38888889 | H10: Usage-Ramp-up als Benefit-Ramp-up
B11: Ramp-up Faktor Y2 | C11: =IFERROR('05_KOSTEN_MODELL'!D9/'05_KOSTEN_MODELL'!F9,0) -> 0.66666667 | D11: =IFERROR('05_KOSTEN_MODELL'!D9/'05_KOSTEN_MODELL'!F9,0) -> 0.66666667 | E11: =IFERROR('05_KOSTEN_MODELL'!D9/'05_KOSTEN_MODELL'!F9,0) -> 0.66666667 | F11: =IFERROR('05_KOSTEN_MODELL'!D9/'05_KOSTEN_MODELL'!F9,0) -> 0.66666667 | G11: =IFERROR('05_KOSTEN_MODELL'!D9/'05_KOSTEN_MODELL'!F9,0) -> 0.66666667 | H11: Usage-Ramp-up als Benefit-Ramp-up
B12: Ramp-up Faktor Y3 | C12: =IFERROR('05_KOSTEN_MODELL'!E9/'05_KOSTEN_MODELL'!F9,0) -> 0.83333333 | D12: =IFERROR('05_KOSTEN_MODELL'!E9/'05_KOSTEN_MODELL'!F9,0) -> 0.83333333 | E12: =IFERROR('05_KOSTEN_MODELL'!E9/'05_KOSTEN_MODELL'!F9,0) -> 0.83333333 | F12: =IFERROR('05_KOSTEN_MODELL'!E9/'05_KOSTEN_MODELL'!F9,0) -> 0.83333333 | G12: =IFERROR('05_KOSTEN_MODELL'!E9/'05_KOSTEN_MODELL'!F9,0) -> 0.83333333 | H12: Usage-Ramp-up als Benefit-Ramp-up
B13: Ramp-up Faktor Y4 | C13: 1 | D13: 1 | E13: 1 | F13: 1 | G13: 1 | H13: Usage-Ramp-up als Benefit-Ramp-up
B14: Ramp-up Faktor Y5 | C14: 1 | D14: 1 | E14: 1 | F14: 1 | G14: 1 | H14: Usage-Ramp-up als Benefit-Ramp-up
B15: 5Y kumulierter Ramp-up-Faktor | C15: =SUM(C10:C14) -> 3.8888889 | D15: =SUM(D10:D14) -> 3.8888889 | E15: =SUM(E10:E14) -> 3.8888889 | F15: =SUM(F10:F14) -> 3.8888889 | G15: =SUM(G10:G14) -> 3.8888889
B16: Kumulierter Nutzen über 5 Jahre | C16: =C9*C15 -> 4695598 | D16: =D9*D15 -> 5248021.3 | E16: =E9*E15 -> 5248021.3 | F16: =F9*F15 -> 4971809.6 | G16: =G9*G15 -> 5248021.3 | H16: 5Y Nutzen über Ramp-up
B17: Einmalige Implementierungsinvestition | C17: ='05_KOSTEN_MODELL'!C67 -> 849830 | D17: ='05_KOSTEN_MODELL'!D67 -> 1149770 | E17: ='05_KOSTEN_MODELL'!E67 -> 1199760 | F17: ='05_KOSTEN_MODELL'!F67 -> 999800 | G17: ='05_KOSTEN_MODELL'!G67 -> 1099780
B18: 5Y OPEX | C18: ='05_KOSTEN_MODELL'!H59 -> 2456048.5 | D18: ='05_KOSTEN_MODELL'!H60 -> 2030628.3 | E18: ='05_KOSTEN_MODELL'!H61 -> 1935236.5 | F18: ='05_KOSTEN_MODELL'!H62 -> 1627150.9 | G18: ='05_KOSTEN_MODELL'!H63 -> 1894791.8
B19: 5Y TCO | C19: =C17+C18 -> 3305878.5 | D19: =D17+D18 -> 3180398.3 | E19: =E17+E18 -> 3134996.5 | F19: =F17+F18 -> 2626950.9 | G19: =G17+G18 -> 2994571.8
B20: 5Y Nettowert | C20: =C16-C19 -> 1389719.5 | D20: =D16-D19 -> 2067623 | E20: =E16-E19 -> 2113024.8 | F20: =F16-F19 -> 2344858.7 | G20: =G16-G19 -> 2253449.4 | H20: Nutzen minus TCO
B21: Nettoeffekt Jahr 1 | C21: =C9*C10-'05_KOSTEN_MODELL'!C59-C17 -> -770925.05 | D21: =D9*D10-'05_KOSTEN_MODELL'!C60-D17 -> -1015153.3 | E21: =E9*E10-'05_KOSTEN_MODELL'!C61-E17 -> -1058817.1 | F21: =F9*F10-'05_KOSTEN_MODELL'!C62-F17 -> -821673.13 | G21: =G9*G10-'05_KOSTEN_MODELL'!C63-G17 -> -941184.06
B22: Payback (Monate, steady state) | C22: =IF((C9-'05_KOSTEN_MODELL'!C70)>0,C17/((C9-'05_KOSTEN_MODELL'!C70)/12),"") -> 15.480308 | D22: =IF((D9-'05_KOSTEN_MODELL'!D70)>0,D17/((D9-'05_KOSTEN_MODELL'!D70)/12),"") -> 14.768145 | E22: =IF((E9-'05_KOSTEN_MODELL'!E70)>0,E17/((E9-'05_KOSTEN_MODELL'!E70)/12),"") -> 14.987287 | F22: =IF((F9-'05_KOSTEN_MODELL'!F70)>0,F17/((F9-'05_KOSTEN_MODELL'!F70)/12),"") -> 12.637145 | G22: =IF((G9-'05_KOSTEN_MODELL'!G70)>0,G17/((G9-'05_KOSTEN_MODELL'!G70)/12),"") -> 13.700926 | H22: Vereinfachter steady-state Payback
B23: 5Y ROI (Netto / TCO) | C23: =IF(C19>0,C20/C19,"") -> 0.42037825 | D23: =IF(D19>0,D20/D19,"") -> 0.65011448 | E23: =IF(E19>0,E20/E19,"") -> 0.67401187 | F23: =IF(F19>0,F20/F19,"") -> 0.89261611 | G23: =IF(G19>0,G20/G19,"") -> 0.7525114
B24: Rang nach 5Y Nettowert | C24: =RANK(C20,$C$20:$G$20,0) -> 5 | D24: =RANK(D20,$C$20:$G$20,0) -> 4 | E24: =RANK(E20,$C$20:$G$20,0) -> 3 | F24: =RANK(F20,$C$20:$G$20,0) -> 1 | G24: =RANK(G20,$C$20:$G$20,0) -> 2
B29: ROI Berechnung
B31: Nutzen | C31: Copilot Studio | D31: Azure Komponenten | E31: Open Source auf Azure | F31: GCP Vertex AI | G31: GCP Komponenten | H31: Kommentar
B32: Nutzen Y1 | C32: =C$9*C10 -> 469559.8 | D32: =D$9*D10 -> 524802.13 | E32: =E$9*E10 -> 524802.13 | F32: =F$9*F10 -> 497180.96 | G32: =G$9*G10 -> 524802.13
B33: Nutzen Y2 | C33: =C$9*C11 -> 804959.66 | D33: =D$9*D11 -> 899660.79 | E33: =E$9*E11 -> 899660.79 | F33: =F$9*F11 -> 852310.22 | G33: =G$9*G11 -> 899660.79
B34: Nutzen Y3 | C34: =C$9*C12 -> 1006199.6 | D34: =D$9*D12 -> 1124576 | E34: =E$9*E12 -> 1124576 | F34: =F$9*F12 -> 1065387.8 | G34: =G$9*G12 -> 1124576
B35: Nutzen Y4 | C35: =C$9*C13 -> 1207439.5 | D35: =D$9*D13 -> 1349491.2 | E35: =E$9*E13 -> 1349491.2 | F35: =F$9*F13 -> 1278465.3 | G35: =G$9*G13 -> 1349491.2
B36: Nutzen Y5 | C36: =C$9*C14 -> 1207439.5 | D36: =D$9*D14 -> 1349491.2 | E36: =E$9*E14 -> 1349491.2 | F36: =F$9*F14 -> 1278465.3 | G36: =G$9*G14 -> 1349491.2
B38: Kosten | C38: Copilot Studio | D38: Azure Komponenten | E38: Open Source auf Azure | F38: GCP Vertex AI | G38: GCP Komponenten | H38: Kommentar
B39: Kosten Y0 | C39: ='05_KOSTEN_MODELL'!C67 -> 849830 | D39: ='05_KOSTEN_MODELL'!D67 -> 1149770 | E39: ='05_KOSTEN_MODELL'!E67 -> 1199760 | F39: ='05_KOSTEN_MODELL'!F67 -> 999800 | G39: ='05_KOSTEN_MODELL'!G67 -> 1099780
B40: Kosten Y1 | C40: ='05_KOSTEN_MODELL'!$C$59 -> 390654.85 | D40: ='05_KOSTEN_MODELL'!$C$60 -> 390185.43 | E40: ='05_KOSTEN_MODELL'!$C$61 -> 383859.25 | F40: ='05_KOSTEN_MODELL'!$C$62 -> 319054.09 | G40: ='05_KOSTEN_MODELL'!$C$63 -> 366206.18
B41: Kosten Y2 | C41: ='05_KOSTEN_MODELL'!$D$59 -> 462479.75 | D41: ='05_KOSTEN_MODELL'!$D$60 -> 401571.31 | E41: ='05_KOSTEN_MODELL'!$D$61 -> 386136.42 | F41: ='05_KOSTEN_MODELL'!$D$62 -> 323608.44 | G41: ='05_KOSTEN_MODELL'!$D$63 -> 375314.89
B42: Kosten Y3 | C42: ='05_KOSTEN_MODELL'!$E$59 -> 505574.69 | D42: ='05_KOSTEN_MODELL'!$E$60 -> 408402.84 | E42: ='05_KOSTEN_MODELL'!$E$61 -> 387502.73 | F42: ='05_KOSTEN_MODELL'!$E$62 -> 326341.05 | G42: ='05_KOSTEN_MODELL'!$E$63 -> 380780.11
B43: Kosten Y4 | C43: ='05_KOSTEN_MODELL'!$F$59 -> 548669.63 | D43: ='05_KOSTEN_MODELL'!$F$60 -> 415234.36 | E43: ='05_KOSTEN_MODELL'!$F$61 -> 388869.03 | F43: ='05_KOSTEN_MODELL'!$F$62 -> 329073.66 | G43: ='05_KOSTEN_MODELL'!$F$63 -> 386245.33
B44: Kosten Y5 | C44: ='05_KOSTEN_MODELL'!$G$59 -> 548669.63 | D44: ='05_KOSTEN_MODELL'!$G$60 -> 415234.36 | E44: ='05_KOSTEN_MODELL'!$G$61 -> 388869.03 | F44: ='05_KOSTEN_MODELL'!$G$62 -> 329073.66 | G44: ='05_KOSTEN_MODELL'!$G$63 -> 386245.33
B46: Break-Even Analyse – Kumulierter Netto-Cashflow
B48: Jahr | C48: Copilot Studio | D48: Azure Komponenten | E48: Open Source auf Azure | F48: GCP Vertex AI | G48: GCP Komponenten | H48: Kommentar
B49: Jahr 0 | C49: =-C39 -> -849830 | D49: =-D39 -> -1149770 | E49: =-E39 -> -1199760 | F49: =-F39 -> -999800 | G49: =-G39 -> -1099780
B50: Jahr 1 | C50: =C49+(C32-C40) -> -770925.05 | D50: =D49+(D32-D40) -> -1015153.3 | E50: =E49+(E32-E40) -> -1058817.1 | F50: =F49+(F32-F40) -> -821673.13 | G50: =G49+(G32-G40) -> -941184.06
B51: Jahr 2 | C51: =C50+(C33-C41) -> -428445.15 | D51: =D50+(D33-D41) -> -517063.82 | E51: =E50+(E33-E41) -> -545292.75 | F51: =F50+(F33-F41) -> -292971.35 | G51: =G50+(G33-G41) -> -416838.15
B52: Jahr 3 | C52: =C51+(C34-C42) -> 72179.733 | D52: =D51+(D34-D42) -> 199109.34 | E52: =E51+(E34-E42) -> 191780.52 | F52: =F51+(F34-F42) -> 446075.38 | G52: =G51+(G34-G42) -> 326957.73
B53: Jahr 4 | C53: =C52+(C35-C43) -> 730949.59 | D53: =D52+(D35-D43) -> 1133366.2 | E53: =E52+(E35-E43) -> 1152402.7 | F53: =F52+(F35-F43) -> 1395467.1 | G53: =G52+(G35-G43) -> 1290203.6
B54: Jahr 5 | C54: =C53+(C36-C44) -> 1389719.5 | D54: =D53+(D36-D44) -> 2067623 | E54: =E53+(E36-E44) -> 2113024.8 | F54: =F53+(F36-F44) -> 2344858.7 | G54: =G53+(G36-G44) -> 2253449.4

Sheet 08_QUELLEN
B2: Quellen, Annahmen und Modellabgrenzungen
B4: Kategorie | C4: Quelle / Referenz | D4: Einsatz im Modell | E4: Hinweis
B5: Copilot Studio Pricing | C5: https://www.microsoft.com/microsoft-365/copilot/pricing/copilot-studio | D5: Preis pro Copilot Credit / Credit-Logik | E5: Öffentliche Microsoft-Seite; tatsächliche Kosten können von Tenant, Kanal und Nutzungsprofil abhängen.
B6: Azure OpenAI Pricing | C6: https://azure.microsoft.com/pricing/details/cognitive-services/openai-service/ | D6: Planungsannahmen für Input-/Output-/Embedding-Preise | E6: Azure weist darauf hin, dass Preise nach Modell, Region, Vertrag und Deployment-Ansatz variieren.
B7: Azure AI Search Pricing | C7: https://azure.microsoft.com/en-us/pricing/details/search/ | D7: Planungsannahmen für Search Units | E7: Workbook nutzt editierbare Annahmen statt harter Listenpreise.
B8: Azure API Management Pricing | C8: https://azure.microsoft.com/pricing/details/api-management/ | D8: Planungsannahme für Gateway / API-Ebene | E8: SKU- und regionsabhängig.
B9: Azure Managed Redis Pricing | C9: https://azure.microsoft.com/en-us/pricing/details/managed-redis/ | D9: Referenz für State / Cache / Memory-Layer | E9: Nicht direkt im Kostenmodell bepreist, aber als Architekturreferenz relevant.
B10: Landi Nutzenannahme | C10: User-provided screenshot / Landi MT2023 | D10: Top-down Referenznutzen (CHF 2.023 Mio. brutto; CHF 1.517 Mio. konservativ) | E10: Im Modell bewusst als Referenzspur erhalten.
B11: Landi operative Annahmen | C11: User-provided screenshot with input parameters | D11: Skalierungs-, Prozess- und Umsatztreiber | E11: In 02_INPUTS zusammengeführt.
B12: Workshop-Schätzung | C12: User upload: 2026_03_16_Workshop_Schaetzung_Digitaler_Assistent.xlsx | D12: Bottom-up Crosscheck | E12: Quantifizierte Workshop-Tasks ergeben rund CHF 2.52 Mio. Bruttonutzen p.a.
B13: Modellabgrenzung | C13: Planning assumption | D13: Open Source und ZenAI sind bewusst parametrisierte Benchmarks | E13: Für finale Entscheidungsreife sollten Vendor-Quotes / Cloud-Quotes ergänzt werden.
B14: Copilot Studio Connectors | C14: https://learn.microsoft.com/en-us/microsoft-copilot-studio/copilot-ai-plugins | D14: Einordnung des Integrationsmodells für Copilot Studio | E14: Zeigt Einsatz von Standard-, Premium- und Custom-Connectors als Tools.
B15: Power Platform On-Prem Gateway | C15: https://learn.microsoft.com/en-us/power-platform/admin/wp-onpremises-gateway | D15: Annahme für Hybrid-/On-Prem-Integrationsfaktor | E15: On-Prem-Anbindung erfordert Gateway-Betrieb, Netzwerk- und Security-Setup; daher Copilot-Systemintegration nicht zu tief angesetzt.
... B44: 100% Generative Annahme (confirmed) | C44: Landi Workshop-Entscheid April 2026 | D44: Alle Use Cases (inkl. Garantie prüfen via ERP) generativ. Anteil generativ Copilot: 0.85 → 1.0. Agent Actions: 2.5 → 3.5. | E44: Impact Copilot: Credits/Interaktion ~14.5 → ~19.65 (+35%). Bei 173K Interaktionen Y4 = +CHF 9K/Jahr Modell-OPEX.

Sheet 09_INPUT_PARAMETER_BC_SAV
B2: Input Parameter
B4: Kategorie | C4: Element | D4: Wert | E4: Bemerkungen
B7: Points-of-Sale & Mitarbeiter
C8: Anzahl PoS | D8: 193 | E8: Konzeptläden XS-XL, Ohne Depot Läden (72 Stück)
C9: Anzahl Service-Mitarbeitende pro PoS | D9: 3 | E9: XS = 2, XL=4
C10: Totale Anzahl Service-Mitarbeitende | D10: 579
C11: Durchschnitts Personalkosten Servicepersonal in CHF/Stunde | D11: 50
C12: Anzahl Öffnungsstunden PoS/Woche | D12: 64 | E12: Anhand Beispiel Landi Mönchaltorf
C13: Anzahl Öffnungsstunden PoS/Montag | D13: 11 | E13: Anhand Beispiel Landi Mönchaltorf
C14: Anzahl Öffnungsstunden PoS/Dienstag | D14: 11 | E14: Anhand Beispiel Landi Mönchaltorf
C15: Anzahl Öffnungsstunden PoS/Mittwoch | D15: 11 | E15: Anhand Beispiel Landi Mönchaltorf
C16: Anzahl Öffnungsstunden PoS/Donnerstag | D16: 11 | E16: Anhand Beispiel Landi Mönchaltorf
C17: Anzahl Öffnungsstunden PoS/Freitag | D17: 11 | E17: Anhand Beispiel Landi Mönchaltorf
C18: Anzahl Öffnungsstunden PoS/Samstag | D18: 9 | E18: Anhand Beispiel Landi Mönchaltorf
C19: Anzahl Arbeitstage PoS/Jahr | D19: 312 | E19: 52 Wochen x 6 Tage/Woche
C20: Anzahl Tage mit reduzierten Öffnungszeiten PoS | D20: 3 | E20: Anhand Beispiel Landi Mönchaltorf
C21: Anzahl Stunden reduzierte Öfnungszeit PoS/Tag | D21: 1 | E21: Anhand Beispiel Landi Mönchaltorf
C22: Anzahl Tage geschlossen PoS/Jahr | D22: 2 | E22: Anhand Beispiel Landi Mönchaltorf
B25: Adoptionsrate
C26: Adoptionsrate des digitalen Assistenten bei den Mitarbeitenden in % | D26: 100 | E26: Verteilt über 2 Jahre (ambitioniert aber machbar)
C27: Adoptionsrate Landi Laden MA | D27: 70% - 100% | E27: variert stark je nach Aufgabe. Muss ev. auch enforced werden
C28: Adoptionsrate Landi CH MA | D28: 95% - 100%
B30: Treffsicherheit
C31: Treffsicherheit des digitalen Assistenten in % | D31: 95-100 | E31: Check mit KI Spezialisten wo die Grenzen liegen für die Akzeptanz durch die Mitarbeitenden
B35: Zeithorizont
C36: Zeithorizont in Jahre | D36: 5 | E36: Ende 2026 Umsetzung fertig. Ab 2027 Rollout. Case rechnen bis Ende 2030
B39: Service
C40: Schriftliche Anfragen und Service-Aufträge pro PoS pro Jahr | D40: 1’399
C41: Schriftliche Anfragen pro PoS pro Jahr | D41: 1’056
C42: Anzahl PoS welche einen Service Auftrag eröffnen | D42: 283 | E42: Quelle: Qliksense Basis 2025 (200 Pos >100 SA/Jahr)
C43: Service-Aufträge pro PoS pro Jahr | D43: 234 | E43: Total SA/Total Anz. PoS mit SA
C44: Schriftliche Anfragen pro Jahr | D44: 203’875
C45: Service-Aufträge pro Jahr | D45: 66’225 | E45: 40% kommen retour, 60% werden an der Front gutgeschrieben
C46: Gutschriften im Service Center | D46: 15’535 | E46: 0.09
C47: Retournierte Service-Aufträge pro Jahr | D47: 50’690 | E47: 31% (50'690) können repariert und retourniert werden. Bei den übrigen 15'535 muss ein Gutschrift erfolgen, weil kein Ersatzteil, nicht reparierbar, totalschaden, etc.
C48: Ziel Wert Einsparung unnötiger Service-Aufträge, in % vom Gesamtanzahl der retournierten Service-Aufträge | D48: 20 | E48: 20% von den 52'468 könnten direkt am PoS gelöst werden und müssten nicht eingeschickt werden
C49: Durchschnittliche Bearbeitungsdauer pro Service-Auftrag, in Minuten | D49: 43.47
C50: Durchschnittliche Bearbeitungsdauer pro unnötiger Service-Auftrag, in Minuten | D50: 23
B52: Zeitersparnis
C53: Zeitersparnis pro Anfrage in % | D53: 33 | E53: Schätzung/Ziel.
C54: Zeitersparnis pro Service-Auftrag in Minuten | D54: 2 | E54: Bezieht sich auf die 66'225 Service-Aufträge
B57: Kunden & Umsatz
C59: Durchschnittsumsatz online Einkauf in CHF | D59: 103 | E59: Basis 2025 (Quelle: Eco Report Q1 2026)
C60: {=online umsatz in chf} -> #NAME? | D60: 20’790’000 | E60: Basis 2025 (Quelle: Eco Report Q1 2026)
C61: Budget / Ziele 2026 Durchschnittsumsatz online Einkauf in CHF | D61: 104.9 | E61: Budget 2026 (Quelle: Eco Report Q1 2026)
C62: = Budget / Ziele 2026 online Umsatz in CHF | D62: 23’707’400 | E62: Budget 2026 (Quelle: Eco Report Q1 2026)
C63: Durchschnittsumsatz pro PoS pro Einkauf in CHF | D63: 37.8 | E63: Basis 2025 (Quelle: LANDI Treuhand)
C64: Durchschnittsumsatz pro PoS im Jahr in CHF | D64: 5’954’000 | E64: Basis 2025 (Quelle: LANDI Treuhand)
C65: Totalumsatz aller PoS im Jahr, in CHF | D65: 1’149’122’000
C66: Durchschnittliche Marge Abgabe an Landi CH, in % | D66: 25.62 | E66: Basis 2025 (Quelle: LANDI Treuhand)
C67: Durchschnittliche Anzahl Kunden pro PoS im Jahr | D67: 157’000 | E67: Basis 2025 (Quelle: LANDI Treuhand)
C68: Anzahl Kunden pro Tag | D68: 503
C69: Anzahl Einkäufe pro Kunde pro Jahr | D69: ??
C70: Steigerung des Einkaufsvolumen in %, pro Einkauf | D70: ??
C71: Steigerung Einkaufsfrequenz in %, pro Jahr | D71: ??
C72: Umsatzsteigerung Ersatzteile in %, pro Jahr
B75: Gutschriften
C76: Totale Anzahl Direktgutschriften pro Jahr | D76: 100’827 | E76: Quelle: Qliksense Basis 2025
C77: Totales Volumen Direktgutschriften pro Jahr in CHF | D77: 2’771’783 | E77: Quelle: Qliksense Basis 2025
C78: Durchschnittliches Direktgutschriftvolumen, in CHF | D78: 27.49
C79: Verhältnis Direktgutschrift vs. Einsenden, ratio in % | D79: 60/40 | E79: Basis 2025
B82: Ersatzteile
C83: Total Umsatz (AP) Ersatzteile pro Jahr | D83: 2’106’028 | E83: Quelle: Qliksense Basis 2025
C84: Total Absatz Ersatzteile pro Jahr | D84: 347’012 | E84: Quelle: Qliksense Basis 2025
C85: Absatz Ersatzteile via Service Aufträge pro Jahr | D85: 110’138 | E85: Quelle: Qliksense Basis 2025
C86: Via Liefer-Tour ausgelieferte Ersatzteile an LANDI Läden pro Jahr | D86: 165’553
C87: Via Post versendete Ersatzteile an LANDI Läden pro Jahr | D87: 71’321 | E87: Quelle: Controlling Rüstauftrag_Postversand & WAETSC_2026, Basisi 2025
C88: Durchschnittlicher Abgabepreis eines Ersatzteiles, in CHF | D88: 6.07 | E88: Total Umsatz (AP) Ersatzteile pro Jahr / Total Absatz Ersatzteile pro Jahr
C89: Durchschnittliche Anzahl Ersatzteile pro Service Auftrag | D89: 1.66
C90: Durschnittliche Einkaufspreis eines Ersatzteiles, in CHF bei einem Serive Auftrag | D90: 5.6 | E90: Total Wert ausgelieferte Menge ET / Total Anzahl ausgelieferte ET, Basis 2025 Quelle: B4LCH Export_Prduom
C91: Durchschnittliche Ersatzteilwert pro Service-Auftrag, in CHF | D91: 9.31 | E91: Einkaufspreis
C92: Schätzung zusätzliche Ersatzteilverkäufe durch bessere Diagnose | D92: 23687.4 | E92: Annahme: 10 % mehr Ersatzteilverkäufe an Endkunden
C93: Schätzung Nutzen (Gewinn pro Ersatzteilverkauf) | D93: 1.5 Chf | E93: Annahme: Im Schnitt 6.- pro Ersatzteil, darauf 25% Marge
B95: Versand
C96: Versandkosten Postversand Ersatzteile von Landi CH zum PoS, pro Service-Auftrag, in CHF | D96: 6.4 | E96: Basis Dez25 - Feb 26 (Quelle: Controlling "WAP_SC_Kosten_2026)
C97: Durschnittliche Kosten pro Versand eines Ersatzteiles, in CHF | D97: 3.85 | E97: Versantkosten / Ø Ersatzteile pro SA.Möglicher Wert wäre auch Total Post Positionen / Total Post Lieferungen
C98: Anzahl Versendete Postsendungen mit ET an PoS pro Jahr | D98: 26’417 | E98: Normale ET Bestellungen (Quelle: Controlling Post und Werkstatt Kommissionierung Basis 2025)
C99: Anzahl versendete ET an PoS pro Jahr | D99: 71’327 | E99: Normale ET Bestellungen (Quelle: Controlling Post und Werkstatt Kommissionierung Basis 2025)
C100: Durchschnittliche Anzahl ET pro Postsendung | D100: 2.7 | E100: Normale ET Bestellungen
B102: Landi.ch
C103: Sitzungen landi.ch | D103: 25’720’000 | E103: Basis 2025 (Quelle: Eco Report Q1 2026)
C104: Budget / Ziele 2026 Sitzungen landi.ch | D104: 28’250’000 | E104: Budget 2026 (Quelle: Eco Report Q1 2026)
C105: Traffic pro Arbeitstag | D105: 70’466
C106: Budget / Ziele 2026 Traffic pro Arbeitstag | D106: 77’397 | E106: Budget 2026 (Quelle: Eco Report Q1 2026)
C107: Conversion Rate aktuell, in Prozent | D107: 0.78 | E107: Basis 2025 (Quelle: Eco Report Q1 2026) Überprüfen der aktuellen Conversion Rate von Anzahl Impressions zu effektiven Bestellungen
C108: Budget / Ziele 2026 Conversion Rate, in Prozent | D108: 0.8 | E108: Budget 2026 (Quelle: Eco Report Q1 2026)
C109: {=anz. bestellungen} -> #NAME? | D109: 201’750 | E109: Basis 2025 (Quelle: Eco Report Q1 2026)
C110: =Budget / Ziele 2026 Anz. Bestellungen | D110: 226’000 | E110: Budget 2026 (Quelle: Eco Report Q1 2026)
C111: Conversion Rate neu, in Prozent | D111: 0.0085 | E111: Gemäss Berechnung Arbeitsblatt CvR iAdvize auf Basis der Prognose/Budget 2026
B113: Landi Laden MA | C113: Anzahl Produktidentifikation pro Tag | D113: 500’000 | E113: Annahme: 10 Fälle pro Tag pro Laden
C114: Anzahl Ersatzteilidentifikation pro Tag | D114: 5’000 | E114: Annahme: 1 von 10 Fällen pro Produktanfrage
